Workbook

Sheet Briefcase cash and runway
A1: Briefcase cash and runway
A2: Briefcase — Runway & decisions · Briefcase Base
A4: Variable / dimension | B4: 2026-09 | C4: 2026-10 | D4: 2026-11 | E4: 2026-12 | F4: 2027-01 | G4: 2027-02 | H4: 2027-03 | I4: 2027-04 | J4: 2027-05 | K4: 2027-06 | L4: 2027-07 | M4: 2027-08 | N4: 2027-09 | O4: 2027-10 | P4: 2027-11 | Q4: 2027-12
A5: Cash balance | B5: ="" | C5: ="" | D5: ="" | E5: ="" | F5: ="" | G5: ="" | H5: ="" | I5: ="" | ... Q5: =""
A6: Bootstrapped — $0 | B6: =IF('Model inputs'!Z121="","",'Model inputs'!Z121) -> 0 | C6: ='Briefcase cash and runway'!B6+'Briefcase conversion and cost s'!B65 -> 1810 | D6: ='Briefcase cash and runway'!C6+'Model inputs'!L83 -> 3620 | E6: ='Briefcase cash and runway'!D6+'Model inputs'!M83 -> 5430 | F6: ='Briefcase cash and runway'!E6+'Model inputs'!N83 -> 7240 | G6: ='Briefcase cash and runway'!F6+'Model inputs'!O83 -> 9050 | H6: ='Briefcase cash and runway'!G6+'Model inputs'!P83 -> 10860 | I6: ='Briefcase cash and runway'!H6+'Model inputs'!Q83 -> 12670 | J6: ='Briefcase cash and runway'!I6+'Model inputs'!R83 -> 14480 | K6: ='Briefcase cash and runway'!J6+'Model inputs'!S83 -> 16290 | ... Q6: ='Briefcase cash and runway'!P6+'Model inputs'!Y83 -> 27150
A7: Illustrative pre-seed — $25,000 | B7: =IF('Model inputs'!Z122="","",'Model inputs'!Z122) -> 25000 | C7: ='Briefcase cash and runway'!B7+'Briefcase conversion and cost s'!B65 -> 26810 | D7: ='Briefcase cash and runway'!C7+'Model inputs'!L83 -> 28620 | E7: ='Briefcase cash and runway'!D7+'Model inputs'!M83 -> 30430 | F7: ='Briefcase cash and runway'!E7+'Model inputs'!N83 -> 32240 | G7: ='Briefcase cash and runway'!F7+'Model inputs'!O83 -> 34050 | H7: ='Briefcase cash and runway'!G7+'Model inputs'!P83 -> 35860 | I7: ='Briefcase cash and runway'!H7+'Model inputs'!Q83 -> 37670 | J7: ='Briefcase cash and runway'!I7+'Model inputs'!R83 -> 39480 | K7: ='Briefcase cash and runway'!J7+'Model inputs'!S83 -> 41290 | ... Q7: ='Briefcase cash and runway'!P7+'Model inputs'!Y83 -> 52150
A8: Lean launch — $5,000 | B8: =IF('Model inputs'!Z123="","",'Model inputs'!Z123) -> 5000 | C8: ='Briefcase cash and runway'!B8+'Briefcase conversion and cost s'!B65 -> 6810 | D8: ='Briefcase cash and runway'!C8+'Model inputs'!L83 -> 8620 | E8: ='Briefcase cash and runway'!D8+'Model inputs'!M83 -> 10430 | F8: ='Briefcase cash and runway'!E8+'Model inputs'!N83 -> 12240 | G8: ='Briefcase cash and runway'!F8+'Model inputs'!O83 -> 14050 | H8: ='Briefcase cash and runway'!G8+'Model inputs'!P83 -> 15860 | I8: ='Briefcase cash and runway'!H8+'Model inputs'!Q83 -> 17670 | J8: ='Briefcase cash and runway'!I8+'Model inputs'!R83 -> 19480 | K8: ='Briefcase cash and runway'!J8+'Model inputs'!S83 -> 21290 | ... Q8: ='Briefcase cash and runway'!P8+'Model inputs'!Y83 -> 32150
A9: Full-allowance cash balance | B9: ="" | C9: ="" | D9: ="" | E9: ="" | F9: ="" | G9: ="" | H9: ="" | I9: ="" | ... Q9: =""
A10: Bootstrapped — $0 | B10: =IF('Model inputs'!Z121="","",'Model inputs'!Z121) -> 0 | C10: ='Briefcase cash and runway'!B10+'Briefcase conversion and cost s'!B77 -> -2018 | D10: ='Briefcase cash and runway'!C10+'Model inputs'!L46 -> -4036 | E10: ='Briefcase cash and runway'!D10+'Model inputs'!M46 -> -6054 | F10: ='Briefcase cash and runway'!E10+'Model inputs'!N46 -> -8072 | G10: ='Briefcase cash and runway'!F10+'Model inputs'!O46 -> -10090 | H10: ='Briefcase cash and runway'!G10+'Model inputs'!P46 -> -12108 | I10: ='Briefcase cash and runway'!H10+'Model inputs'!Q46 -> -14126 | J10: ='Briefcase cash and runway'!I10+'Model inputs'!R46 -> -16144 | K10: ='Briefcase cash and runway'!J10+'Model inputs'!S46 -> -18162 | ... Q10: ='Briefcase cash and runway'!P10+'Model inputs'!Y46 -> -30270
A11: Illustrative pre-seed — $25,000 | B11: =IF('Model inputs'!Z122="","",'Model inputs'!Z122) -> 25000 | C11: ='Briefcase cash and runway'!B11+'Briefcase conversion and cost s'!B77 -> 22982 | D11: ='Briefcase cash and runway'!C11+'Model inputs'!L46 -> 20964 | E11: ='Briefcase cash and runway'!D11+'Model inputs'!M46 -> 18946 | F11: ='Briefcase cash and runway'!E11+'Model inputs'!N46 -> 16928 | G11: ='Briefcase cash and runway'!F11+'Model inputs'!O46 -> 14910 | H11: ='Briefcase cash and runway'!G11+'Model inputs'!P46 -> 12892 | I11: ='Briefcase cash and runway'!H11+'Model inputs'!Q46 -> 10874 | J11: ='Briefcase cash and runway'!I11+'Model inputs'!R46 -> 8856 | K11: ='Briefcase cash and runway'!J11+'Model inputs'!S46 -> 6838 | ... Q11: ='Briefcase cash and runway'!P11+'Model inputs'!Y46 -> -5270
A12: Lean launch — $5,000 | B12: =IF('Model inputs'!Z123="","",'Model inputs'!Z123) -> 5000 | C12: ='Briefcase cash and runway'!B12+'Briefcase conversion and cost s'!B77 -> 2982 | D12: ='Briefcase cash and runway'!C12+'Model inputs'!L46 -> 964 | E12: ='Briefcase cash and runway'!D12+'Model inputs'!M46 -> -1054 | F12: ='Briefcase cash and runway'!E12+'Model inputs'!N46 -> -3072 | G12: ='Briefcase cash and runway'!F12+'Model inputs'!O46 -> -5090 | H12: ='Briefcase cash and runway'!G12+'Model inputs'!P46 -> -7108 | I12: ='Briefcase cash and runway'!H12+'Model inputs'!Q46 -> -9126 | J12: ='Briefcase cash and runway'!I12+'Model inputs'!R46 -> -11144 | K12: ='Briefcase cash and runway'!J12+'Model inputs'!S46 -> -13162 | ... Q12: ='Briefcase cash and runway'!P12+'Model inputs'!Y46 -> -25270
A13: Runway from launch in months | B13: =SUM('Briefcase cash and runway'!B14,'Briefcase cash and runway'!B15,'Briefcase cash and runway'!B16) -> 0 | C13: ="" | D13: ="" | E13: ="" | F13: ="" | G13: ="" | H13: ="" | I13: ="" | J13: ="" | ... Q13: =""
A14: Bootstrapped — $0 | B14: =0 -> 0 | C14: =IF(IF(IF(ISERROR('Briefcase conversion and cost s'!B65<0),'Briefcase conversion and cost s'!B65<0,IF('Briefcase conversion and cost s'!B65="","",'Briefcase conversion and cost s'!B65<0))="",FALSE,IF(ISERROR('Briefcase conversion and cost s'!B65<0),'Briefcase conversion and cost s'!B65<0,IF('Briefcase conversion and cost s'!B65="","",'Briefcase conversion and cost s'!B65<0))),'Model inputs'!Z121/-'Briefcase conversion and cost s'!B65,"") | D14: =IF(IF(IF(ISERROR('Model inputs'!L83<0),'Model inputs'!L83<0,IF('Model inputs'!L83="","",'Model inputs'!L83<0))="",FALSE,IF(ISERROR('Model inputs'!L83<0),'Model inputs'!L83<0,IF('Model inputs'!L83="","",'Model inputs'!L83<0))),'Model inputs'!Z121/-'Model inputs'!L83,"") | E14: =IF(IF(IF(ISERROR('Model inputs'!M83<0),'Model inputs'!M83<0,IF('Model inputs'!M83="","",'Model inputs'!M83<0))="",FALSE,IF(ISERROR('Model inputs'!M83<0),'Model inputs'!M83<0,IF('Model inputs'!M83="","",'Model inputs'!M83<0))),'Model inputs'!Z121/-'Model inputs'!M83,"") | F14: =IF(IF(IF(ISERROR('Model inputs'!N83<0),'Model inputs'!N83<0,IF('Model inputs'!N83="","",'Model inputs'!N83<0))="",FALSE,IF(ISERROR('Model inputs'!N83<0),'Model inputs'!N83<0,IF('Model inputs'!N83="","",'Model inputs'!N83<0))),'Model inputs'!Z121/-'Model inputs'!N83,"") | G14: =IF(IF(IF(ISERROR('Model inputs'!O83<0),'Model inputs'!O83<0,IF('Model inputs'!O83="","",'Model inputs'!O83<0))="",FALSE,IF(ISERROR('Model inputs'!O83<0),'Model inputs'!O83<0,IF('Model inputs'!O83="","",'Model inputs'!O83<0))),'Model inputs'!Z121/-'Model inputs'!O83,"") | H14: =IF(IF(IF(ISERROR('Model inputs'!P83<0),'Model inputs'!P83<0,IF('Model inputs'!P83="","",'Model inputs'!P83<0))="",FALSE,IF(ISERROR('Model inputs'!P83<0),'Model inputs'!P83<0,IF('Model inputs'!P83="","",'Model inputs'!P83<0))),'Model inputs'!Z121/-'Model inputs'!P83,"") | I14: =IF(IF(IF(ISERROR('Model inputs'!Q83<0),'Model inputs'!Q83<0,IF('Model inputs'!Q83="","",'Model inputs'!Q83<0))="",FALSE,IF(ISERROR('Model inputs'!Q83<0),'Model inputs'!Q83<0,IF('Model inputs'!Q83="","",'Model inputs'!Q83<0))),'Model inputs'!Z121/-'Model inputs'!Q83,"") | J14: =IF(IF(IF(ISERROR('Model inputs'!R83<0),'Model inputs'!R83<0,IF('Model inputs'!R83="","",'Model inputs'!R83<0))="",FALSE,IF(ISERROR('Model inputs'!R83<0),'Model inputs'!R83<0,IF('Model inputs'!R83="","",'Model inputs'!R83<0))),'Model inputs'!Z121/-'Model inputs'!R83,"") | K14: =IF(IF(IF(ISERROR('Model inputs'!S83<0),'Model inputs'!S83<0,IF('Model inputs'!S83="","",'Model inputs'!S83<0))="",FALSE,IF(ISERROR('Model inputs'!S83<0),'Model inputs'!S83<0,IF('Model inputs'!S83="","",'Model inputs'!S83<0))),'Model inputs'!Z121/-'Model inputs'!S83,"") | L14: =IF(IF(IF(ISERROR('Model inputs'!T83<0),'Model inputs'!T83<0,IF('Model inputs'!T83="","",'Model inputs'!T83<0))="",FALSE,IF(ISERROR('Model inputs'!T83<0),'Model inputs'!T83<0,IF('Model inputs'!T83="","",'Model inputs'!T83<0))),'Model inputs'!Z121/-'Model inputs'!T83,"") | M14: =IF(IF(IF(ISERROR('Model inputs'!U83<0),'Model inputs'!U83<0,IF('Model inputs'!U83="","",'Model inputs'!U83<0))="",FALSE,IF(ISERROR('Model inputs'!U83<0),'Model inputs'!U83<0,IF('Model inputs'!U83="","",'Model inputs'!U83<0))),'Model inputs'!Z121/-'Model inputs'!U83,"") | N14: =IF(IF(IF(ISERROR('Model inputs'!V83<0),'Model inputs'!V83<0,IF('Model inputs'!V83="","",'Model inputs'!V83<0))="",FALSE,IF(ISERROR('Model inputs'!V83<0),'Model inputs'!V83<0,IF('Model inputs'!V83="","",'Model inputs'!V83<0))),'Model inputs'!Z121/-'Model inputs'!V83,"") | O14: =IF(IF(IF(ISERROR('Model inputs'!W83<0),'Model inputs'!W83<0,IF('Model inputs'!W83="","",'Model inputs'!W83<0))="",FALSE,IF(ISERROR('Model inputs'!W83<0),'Model inputs'!W83<0,IF('Model inputs'!W83="","",'Model inputs'!W83<0))),'Model inputs'!Z121/-'Model inputs'!W83,"") | P14: =IF(IF(IF(ISERROR('Model inputs'!X83<0),'Model inputs'!X83<0,IF('Model inputs'!X83="","",'Model inputs'!X83<0))="",FALSE,IF(ISERROR('Model inputs'!X83<0),'Model inputs'!X83<0,IF('Model inputs'!X83="","",'Model inputs'!X83<0))),'Model inputs'!Z121/-'Model inputs'!X83,"") | Q14: =IF(IF(IF(ISERROR('Model inputs'!Y83<0),'Model inputs'!Y83<0,IF('Model inputs'!Y83="","",'Model inputs'!Y83<0))="",FALSE,IF(ISERROR('Model inputs'!Y83<0),'Model inputs'!Y83<0,IF('Model inputs'!Y83="","",'Model inputs'!Y83<0))),'Model inputs'!Z121/-'Model inputs'!Y83,"")
A15: Illustrative pre-seed — $25,000 | B15: =0 -> 0 | C15: =IF(IF(IF(ISERROR('Briefcase conversion and cost s'!B65<0),'Briefcase conversion and cost s'!B65<0,IF('Briefcase conversion and cost s'!B65="","",'Briefcase conversion and cost s'!B65<0))="",FALSE,IF(ISERROR('Briefcase conversion and cost s'!B65<0),'Briefcase conversion and cost s'!B65<0,IF('Briefcase conversion and cost s'!B65="","",'Briefcase conversion and cost s'!B65<0))),'Model inputs'!Z122/-'Briefcase conversion and cost s'!B65,"") | D15: =IF(IF(IF(ISERROR('Model inputs'!L83<0),'Model inputs'!L83<0,IF('Model inputs'!L83="","",'Model inputs'!L83<0))="",FALSE,IF(ISERROR('Model inputs'!L83<0),'Model inputs'!L83<0,IF('Model inputs'!L83="","",'Model inputs'!L83<0))),'Model inputs'!Z122/-'Model inputs'!L83,"") | E15: =IF(IF(IF(ISERROR('Model inputs'!M83<0),'Model inputs'!M83<0,IF('Model inputs'!M83="","",'Model inputs'!M83<0))="",FALSE,IF(ISERROR('Model inputs'!M83<0),'Model inputs'!M83<0,IF('Model inputs'!M83="","",'Model inputs'!M83<0))),'Model inputs'!Z122/-'Model inputs'!M83,"") | F15: =IF(IF(IF(ISERROR('Model inputs'!N83<0),'Model inputs'!N83<0,IF('Model inputs'!N83="","",'Model inputs'!N83<0))="",FALSE,IF(ISERROR('Model inputs'!N83<0),'Model inputs'!N83<0,IF('Model inputs'!N83="","",'Model inputs'!N83<0))),'Model inputs'!Z122/-'Model inputs'!N83,"") | G15: =IF(IF(IF(ISERROR('Model inputs'!O83<0),'Model inputs'!O83<0,IF('Model inputs'!O83="","",'Model inputs'!O83<0))="",FALSE,IF(ISERROR('Model inputs'!O83<0),'Model inputs'!O83<0,IF('Model inputs'!O83="","",'Model inputs'!O83<0))),'Model inputs'!Z122/-'Model inputs'!O83,"") | H15: =IF(IF(IF(ISERROR('Model inputs'!P83<0),'Model inputs'!P83<0,IF('Model inputs'!P83="","",'Model inputs'!P83<0))="",FALSE,IF(ISERROR('Model inputs'!P83<0),'Model inputs'!P83<0,IF('Model inputs'!P83="","",'Model inputs'!P83<0))),'Model inputs'!Z122/-'Model inputs'!P83,"") | I15: =IF(IF(IF(ISERROR('Model inputs'!Q83<0),'Model inputs'!Q83<0,IF('Model inputs'!Q83="","",'Model inputs'!Q83<0))="",FALSE,IF(ISERROR('Model inputs'!Q83<0),'Model inputs'!Q83<0,IF('Model inputs'!Q83="","",'Model inputs'!Q83<0))),'Model inputs'!Z122/-'Model inputs'!Q83,"") | J15: =IF(IF(IF(ISERROR('Model inputs'!R83<0),'Model inputs'!R83<0,IF('Model inputs'!R83="","",'Model inputs'!R83<0))="",FALSE,IF(ISERROR('Model inputs'!R83<0),'Model inputs'!R83<0,IF('Model inputs'!R83="","",'Model inputs'!R83<0))),'Model inputs'!Z122/-'Model inputs'!R83,"") | K15: =IF(IF(IF(ISERROR('Model inputs'!S83<0),'Model inputs'!S83<0,IF('Model inputs'!S83="","",'Model inputs'!S83<0))="",FALSE,IF(ISERROR('Model inputs'!S83<0),'Model inputs'!S83<0,IF('Model inputs'!S83="","",'Model inputs'!S83<0))),'Model inputs'!Z122/-'Model inputs'!S83,"") | L15: =IF(IF(IF(ISERROR('Model inputs'!T83<0),'Model inputs'!T83<0,IF('Model inputs'!T83="","",'Model inputs'!T83<0))="",FALSE,IF(ISERROR('Model inputs'!T83<0),'Model inputs'!T83<0,IF('Model inputs'!T83="","",'Model inputs'!T83<0))),'Model inputs'!Z122/-'Model inputs'!T83,"") | M15: =IF(IF(IF(ISERROR('Model inputs'!U83<0),'Model inputs'!U83<0,IF('Model inputs'!U83="","",'Model inputs'!U83<0))="",FALSE,IF(ISERROR('Model inputs'!U83<0),'Model inputs'!U83<0,IF('Model inputs'!U83="","",'Model inputs'!U83<0))),'Model inputs'!Z122/-'Model inputs'!U83,"") | N15: =IF(IF(IF(ISERROR('Model inputs'!V83<0),'Model inputs'!V83<0,IF('Model inputs'!V83="","",'Model inputs'!V83<0))="",FALSE,IF(ISERROR('Model inputs'!V83<0),'Model inputs'!V83<0,IF('Model inputs'!V83="","",'Model inputs'!V83<0))),'Model inputs'!Z122/-'Model inputs'!V83,"") | O15: =IF(IF(IF(ISERROR('Model inputs'!W83<0),'Model inputs'!W83<0,IF('Model inputs'!W83="","",'Model inputs'!W83<0))="",FALSE,IF(ISERROR('Model inputs'!W83<0),'Model inputs'!W83<0,IF('Model inputs'!W83="","",'Model inputs'!W83<0))),'Model inputs'!Z122/-'Model inputs'!W83,"") | P15: =IF(IF(IF(ISERROR('Model inputs'!X83<0),'Model inputs'!X83<0,IF('Model inputs'!X83="","",'Model inputs'!X83<0))="",FALSE,IF(ISERROR('Model inputs'!X83<0),'Model inputs'!X83<0,IF('Model inputs'!X83="","",'Model inputs'!X83<0))),'Model inputs'!Z122/-'Model inputs'!X83,"") | Q15: =IF(IF(IF(ISERROR('Model inputs'!Y83<0),'Model inputs'!Y83<0,IF('Model inputs'!Y83="","",'Model inputs'!Y83<0))="",FALSE,IF(ISERROR('Model inputs'!Y83<0),'Model inputs'!Y83<0,IF('Model inputs'!Y83="","",'Model inputs'!Y83<0))),'Model inputs'!Z122/-'Model inputs'!Y83,"")
A16: Lean launch — $5,000 | B16: =0 -> 0 | C16: =IF(IF(IF(ISERROR('Briefcase conversion and cost s'!B65<0),'Briefcase conversion and cost s'!B65<0,IF('Briefcase conversion and cost s'!B65="","",'Briefcase conversion and cost s'!B65<0))="",FALSE,IF(ISERROR('Briefcase conversion and cost s'!B65<0),'Briefcase conversion and cost s'!B65<0,IF('Briefcase conversion and cost s'!B65="","",'Briefcase conversion and cost s'!B65<0))),'Model inputs'!Z123/-'Briefcase conversion and cost s'!B65,"") | D16: =IF(IF(IF(ISERROR('Model inputs'!L83<0),'Model inputs'!L83<0,IF('Model inputs'!L83="","",'Model inputs'!L83<0))="",FALSE,IF(ISERROR('Model inputs'!L83<0),'Model inputs'!L83<0,IF('Model inputs'!L83="","",'Model inputs'!L83<0))),'Model inputs'!Z123/-'Model inputs'!L83,"") | E16: =IF(IF(IF(ISERROR('Model inputs'!M83<0),'Model inputs'!M83<0,IF('Model inputs'!M83="","",'Model inputs'!M83<0))="",FALSE,IF(ISERROR('Model inputs'!M83<0),'Model inputs'!M83<0,IF('Model inputs'!M83="","",'Model inputs'!M83<0))),'Model inputs'!Z123/-'Model inputs'!M83,"") | F16: =IF(IF(IF(ISERROR('Model inputs'!N83<0),'Model inputs'!N83<0,IF('Model inputs'!N83="","",'Model inputs'!N83<0))="",FALSE,IF(ISERROR('Model inputs'!N83<0),'Model inputs'!N83<0,IF('Model inputs'!N83="","",'Model inputs'!N83<0))),'Model inputs'!Z123/-'Model inputs'!N83,"") | G16: =IF(IF(IF(ISERROR('Model inputs'!O83<0),'Model inputs'!O83<0,IF('Model inputs'!O83="","",'Model inputs'!O83<0))="",FALSE,IF(ISERROR('Model inputs'!O83<0),'Model inputs'!O83<0,IF('Model inputs'!O83="","",'Model inputs'!O83<0))),'Model inputs'!Z123/-'Model inputs'!O83,"") | H16: =IF(IF(IF(ISERROR('Model inputs'!P83<0),'Model inputs'!P83<0,IF('Model inputs'!P83="","",'Model inputs'!P83<0))="",FALSE,IF(ISERROR('Model inputs'!P83<0),'Model inputs'!P83<0,IF('Model inputs'!P83="","",'Model inputs'!P83<0))),'Model inputs'!Z123/-'Model inputs'!P83,"") | I16: =IF(IF(IF(ISERROR('Model inputs'!Q83<0),'Model inputs'!Q83<0,IF('Model inputs'!Q83="","",'Model inputs'!Q83<0))="",FALSE,IF(ISERROR('Model inputs'!Q83<0),'Model inputs'!Q83<0,IF('Model inputs'!Q83="","",'Model inputs'!Q83<0))),'Model inputs'!Z123/-'Model inputs'!Q83,"") | J16: =IF(IF(IF(ISERROR('Model inputs'!R83<0),'Model inputs'!R83<0,IF('Model inputs'!R83="","",'Model inputs'!R83<0))="",FALSE,IF(ISERROR('Model inputs'!R83<0),'Model inputs'!R83<0,IF('Model inputs'!R83="","",'Model inputs'!R83<0))),'Model inputs'!Z123/-'Model inputs'!R83,"") | K16: =IF(IF(IF(ISERROR('Model inputs'!S83<0),'Model inputs'!S83<0,IF('Model inputs'!S83="","",'Model inputs'!S83<0))="",FALSE,IF(ISERROR('Model inputs'!S83<0),'Model inputs'!S83<0,IF('Model inputs'!S83="","",'Model inputs'!S83<0))),'Model inputs'!Z123/-'Model inputs'!S83,"") | L16: =IF(IF(IF(ISERROR('Model inputs'!T83<0),'Model inputs'!T83<0,IF('Model inputs'!T83="","",'Model inputs'!T83<0))="",FALSE,IF(ISERROR('Model inputs'!T83<0),'Model inputs'!T83<0,IF('Model inputs'!T83="","",'Model inputs'!T83<0))),'Model inputs'!Z123/-'Model inputs'!T83,"") | M16: =IF(IF(IF(ISERROR('Model inputs'!U83<0),'Model inputs'!U83<0,IF('Model inputs'!U83="","",'Model inputs'!U83<0))="",FALSE,IF(ISERROR('Model inputs'!U83<0),'Model inputs'!U83<0,IF('Model inputs'!U83="","",'Model inputs'!U83<0))),'Model inputs'!Z123/-'Model inputs'!U83,"") | N16: =IF(IF(IF(ISERROR('Model inputs'!V83<0),'Model inputs'!V83<0,IF('Model inputs'!V83="","",'Model inputs'!V83<0))="",FALSE,IF(ISERROR('Model inputs'!V83<0),'Model inputs'!V83<0,IF('Model inputs'!V83="","",'Model inputs'!V83<0))),'Model inputs'!Z123/-'Model inputs'!V83,"") | O16: =IF(IF(IF(ISERROR('Model inputs'!W83<0),'Model inputs'!W83<0,IF('Model inputs'!W83="","",'Model inputs'!W83<0))="",FALSE,IF(ISERROR('Model inputs'!W83<0),'Model inputs'!W83<0,IF('Model inputs'!W83="","",'Model inputs'!W83<0))),'Model inputs'!Z123/-'Model inputs'!W83,"") | P16: =IF(IF(IF(ISERROR('Model inputs'!X83<0),'Model inputs'!X83<0,IF('Model inputs'!X83="","",'Model inputs'!X83<0))="",FALSE,IF(ISERROR('Model inputs'!X83<0),'Model inputs'!X83<0,IF('Model inputs'!X83="","",'Model inputs'!X83<0))),'Model inputs'!Z123/-'Model inputs'!X83,"") | Q16: =IF(IF(IF(ISERROR('Model inputs'!Y83<0),'Model inputs'!Y83<0,IF('Model inputs'!Y83="","",'Model inputs'!Y83<0))="",FALSE,IF(ISERROR('Model inputs'!Y83<0),'Model inputs'!Y83<0,IF('Model inputs'!Y83="","",'Model inputs'!Y83<0))),'Model inputs'!Z123/-'Model inputs'!Y83,"")
A17: Full-allowance runway in months | B17: =SUM('Briefcase cash and runway'!B18,'Briefcase cash and runway'!B19,'Briefcase cash and runway'!B20) -> 0 | C17: ="" | D17: ="" | E17: ="" | F17: ="" | G17: ="" | H17: ="" | I17: ="" | J17: ="" | ... Q17: =""
A18: Bootstrapped — $0 | B18: =0 -> 0 | C18: =IF(IF(IF(ISERROR('Briefcase conversion and cost s'!B77<0),'Briefcase conversion and cost s'!B77<0,IF('Briefcase conversion and cost s'!B77="","",'Briefcase conversion and cost s'!B77<0))="",FALSE,IF(ISERROR('Briefcase conversion and cost s'!B77<0),'Briefcase conversion and cost s'!B77<0,IF('Briefcase conversion and cost s'!B77="","",'Briefcase conversion and cost s'!B77<0))),'Model inputs'!Z121/-'Briefcase conversion and cost s'!B77,"") -> 0 | D18: =IF(IF(IF(ISERROR('Model inputs'!L46<0),'Model inputs'!L46<0,IF('Model inputs'!L46="","",'Model inputs'!L46<0))="",FALSE,IF(ISERROR('Model inputs'!L46<0),'Model inputs'!L46<0,IF('Model inputs'!L46="","",'Model inputs'!L46<0))),'Model inputs'!Z121/-'Model inputs'!L46,"") -> 0 | E18: =IF(IF(IF(ISERROR('Model inputs'!M46<0),'Model inputs'!M46<0,IF('Model inputs'!M46="","",'Model inputs'!M46<0))="",FALSE,IF(ISERROR('Model inputs'!M46<0),'Model inputs'!M46<0,IF('Model inputs'!M46="","",'Model inputs'!M46<0))),'Model inputs'!Z121/-'Model inputs'!M46,"") -> 0 | F18: =IF(IF(IF(ISERROR('Model inputs'!N46<0),'Model inputs'!N46<0,IF('Model inputs'!N46="","",'Model inputs'!N46<0))="",FALSE,IF(ISERROR('Model inputs'!N46<0),'Model inputs'!N46<0,IF('Model inputs'!N46="","",'Model inputs'!N46<0))),'Model inputs'!Z121/-'Model inputs'!N46,"") -> 0 | G18: =IF(IF(IF(ISERROR('Model inputs'!O46<0),'Model inputs'!O46<0,IF('Model inputs'!O46="","",'Model inputs'!O46<0))="",FALSE,IF(ISERROR('Model inputs'!O46<0),'Model inputs'!O46<0,IF('Model inputs'!O46="","",'Model inputs'!O46<0))),'Model inputs'!Z121/-'Model inputs'!O46,"") -> 0 | H18: =IF(IF(IF(ISERROR('Model inputs'!P46<0),'Model inputs'!P46<0,IF('Model inputs'!P46="","",'Model inputs'!P46<0))="",FALSE,IF(ISERROR('Model inputs'!P46<0),'Model inputs'!P46<0,IF('Model inputs'!P46="","",'Model inputs'!P46<0))),'Model inputs'!Z121/-'Model inputs'!P46,"") -> 0 | I18: =IF(IF(IF(ISERROR('Model inputs'!Q46<0),'Model inputs'!Q46<0,IF('Model inputs'!Q46="","",'Model inputs'!Q46<0))="",FALSE,IF(ISERROR('Model inputs'!Q46<0),'Model inputs'!Q46<0,IF('Model inputs'!Q46="","",'Model inputs'!Q46<0))),'Model inputs'!Z121/-'Model inputs'!Q46,"") -> 0 | J18: =IF(IF(IF(ISERROR('Model inputs'!R46<0),'Model inputs'!R46<0,IF('Model inputs'!R46="","",'Model inputs'!R46<0))="",FALSE,IF(ISERROR('Model inputs'!R46<0),'Model inputs'!R46<0,IF('Model inputs'!R46="","",'Model inputs'!R46<0))),'Model inputs'!Z121/-'Model inputs'!R46,"") -> 0 | K18: =IF(IF(IF(ISERROR('Model inputs'!S46<0),'Model inputs'!S46<0,IF('Model inputs'!S46="","",'Model inputs'!S46<0))="",FALSE,IF(ISERROR('Model inputs'!S46<0),'Model inputs'!S46<0,IF('Model inputs'!S46="","",'Model inputs'!S46<0))),'Model inputs'!Z121/-'Model inputs'!S46,"") -> 0 | L18: =IF(IF(IF(ISERROR('Model inputs'!T46<0),'Model inputs'!T46<0,IF('Model inputs'!T46="","",'Model inputs'!T46<0))="",FALSE,IF(ISERROR('Model inputs'!T46<0),'Model inputs'!T46<0,IF('Model inputs'!T46="","",'Model inputs'!T46<0))),'Model inputs'!Z121/-'Model inputs'!T46,"") -> 0 | M18: =IF(IF(IF(ISERROR('Model inputs'!U46<0),'Model inputs'!U46<0,IF('Model inputs'!U46="","",'Model inputs'!U46<0))="",FALSE,IF(ISERROR('Model inputs'!U46<0),'Model inputs'!U46<0,IF('Model inputs'!U46="","",'Model inputs'!U46<0))),'Model inputs'!Z121/-'Model inputs'!U46,"") -> 0 | N18: =IF(IF(IF(ISERROR('Model inputs'!V46<0),'Model inputs'!V46<0,IF('Model inputs'!V46="","",'Model inputs'!V46<0))="",FALSE,IF(ISERROR('Model inputs'!V46<0),'Model inputs'!V46<0,IF('Model inputs'!V46="","",'Model inputs'!V46<0))),'Model inputs'!Z121/-'Model inputs'!V46,"") -> 0 | O18: =IF(IF(IF(ISERROR('Model inputs'!W46<0),'Model inputs'!W46<0,IF('Model inputs'!W46="","",'Model inputs'!W46<0))="",FALSE,IF(ISERROR('Model inputs'!W46<0),'Model inputs'!W46<0,IF('Model inputs'!W46="","",'Model inputs'!W46<0))),'Model inputs'!Z121/-'Model inputs'!W46,"") -> 0 | P18: =IF(IF(IF(ISERROR('Model inputs'!X46<0),'Model inputs'!X46<0,IF('Model inputs'!X46="","",'Model inputs'!X46<0))="",FALSE,IF(ISERROR('Model inputs'!X46<0),'Model inputs'!X46<0,IF('Model inputs'!X46="","",'Model inputs'!X46<0))),'Model inputs'!Z121/-'Model inputs'!X46,"") -> 0 | Q18: =IF(IF(IF(ISERROR('Model inputs'!Y46<0),'Model inputs'!Y46<0,IF('Model inputs'!Y46="","",'Model inputs'!Y46<0))="",FALSE,IF(ISERROR('Model inputs'!Y46<0),'Model inputs'!Y46<0,IF('Model inputs'!Y46="","",'Model inputs'!Y46<0))),'Model inputs'!Z121/-'Model inputs'!Y46,"") -> 0
A19: Illustrative pre-seed — $25,000 | B19: =0 -> 0 | C19: =IF(IF(IF(ISERROR('Briefcase conversion and cost s'!B77<0),'Briefcase conversion and cost s'!B77<0,IF('Briefcase conversion and cost s'!B77="","",'Briefcase conversion and cost s'!B77<0))="",FALSE,IF(ISERROR('Briefcase conversion and cost s'!B77<0),'Briefcase conversion and cost s'!B77<0,IF('Briefcase conversion and cost s'!B77="","",'Briefcase conversion and cost s'!B77<0))),'Model inputs'!Z122/-'Briefcase conversion and cost s'!B77,"") -> 12.388503 | D19: =IF(IF(IF(ISERROR('Model inputs'!L46<0),'Model inputs'!L46<0,IF('Model inputs'!L46="","",'Model inputs'!L46<0))="",FALSE,IF(ISERROR('Model inputs'!L46<0),'Model inputs'!L46<0,IF('Model inputs'!L46="","",'Model inputs'!L46<0))),'Model inputs'!Z122/-'Model inputs'!L46,"") -> 12.388503 | E19: =IF(IF(IF(ISERROR('Model inputs'!M46<0),'Model inputs'!M46<0,IF('Model inputs'!M46="","",'Model inputs'!M46<0))="",FALSE,IF(ISERROR('Model inputs'!M46<0),'Model inputs'!M46<0,IF('Model inputs'!M46="","",'Model inputs'!M46<0))),'Model inputs'!Z122/-'Model inputs'!M46,"") -> 12.388503 | F19: =IF(IF(IF(ISERROR('Model inputs'!N46<0),'Model inputs'!N46<0,IF('Model inputs'!N46="","",'Model inputs'!N46<0))="",FALSE,IF(ISERROR('Model inputs'!N46<0),'Model inputs'!N46<0,IF('Model inputs'!N46="","",'Model inputs'!N46<0))),'Model inputs'!Z122/-'Model inputs'!N46,"") -> 12.388503 | G19: =IF(IF(IF(ISERROR('Model inputs'!O46<0),'Model inputs'!O46<0,IF('Model inputs'!O46="","",'Model inputs'!O46<0))="",FALSE,IF(ISERROR('Model inputs'!O46<0),'Model inputs'!O46<0,IF('Model inputs'!O46="","",'Model inputs'!O46<0))),'Model inputs'!Z122/-'Model inputs'!O46,"") -> 12.388503 | H19: =IF(IF(IF(ISERROR('Model inputs'!P46<0),'Model inputs'!P46<0,IF('Model inputs'!P46="","",'Model inputs'!P46<0))="",FALSE,IF(ISERROR('Model inputs'!P46<0),'Model inputs'!P46<0,IF('Model inputs'!P46="","",'Model inputs'!P46<0))),'Model inputs'!Z122/-'Model inputs'!P46,"") -> 12.388503 | I19: =IF(IF(IF(ISERROR('Model inputs'!Q46<0),'Model inputs'!Q46<0,IF('Model inputs'!Q46="","",'Model inputs'!Q46<0))="",FALSE,IF(ISERROR('Model inputs'!Q46<0),'Model inputs'!Q46<0,IF('Model inputs'!Q46="","",'Model inputs'!Q46<0))),'Model inputs'!Z122/-'Model inputs'!Q46,"") -> 12.388503 | J19: =IF(IF(IF(ISERROR('Model inputs'!R46<0),'Model inputs'!R46<0,IF('Model inputs'!R46="","",'Model inputs'!R46<0))="",FALSE,IF(ISERROR('Model inputs'!R46<0),'Model inputs'!R46<0,IF('Model inputs'!R46="","",'Model inputs'!R46<0))),'Model inputs'!Z122/-'Model inputs'!R46,"") -> 12.388503 | K19: =IF(IF(IF(ISERROR('Model inputs'!S46<0),'Model inputs'!S46<0,IF('Model inputs'!S46="","",'Model inputs'!S46<0))="",FALSE,IF(ISERROR('Model inputs'!S46<0),'Model inputs'!S46<0,IF('Model inputs'!S46="","",'Model inputs'!S46<0))),'Model inputs'!Z122/-'Model inputs'!S46,"") -> 12.388503 | L19: =IF(IF(IF(ISERROR('Model inputs'!T46<0),'Model inputs'!T46<0,IF('Model inputs'!T46="","",'Model inputs'!T46<0))="",FALSE,IF(ISERROR('Model inputs'!T46<0),'Model inputs'!T46<0,IF('Model inputs'!T46="","",'Model inputs'!T46<0))),'Model inputs'!Z122/-'Model inputs'!T46,"") -> 12.388503 | M19: =IF(IF(IF(ISERROR('Model inputs'!U46<0),'Model inputs'!U46<0,IF('Model inputs'!U46="","",'Model inputs'!U46<0))="",FALSE,IF(ISERROR('Model inputs'!U46<0),'Model inputs'!U46<0,IF('Model inputs'!U46="","",'Model inputs'!U46<0))),'Model inputs'!Z122/-'Model inputs'!U46,"") -> 12.388503 | N19: =IF(IF(IF(ISERROR('Model inputs'!V46<0),'Model inputs'!V46<0,IF('Model inputs'!V46="","",'Model inputs'!V46<0))="",FALSE,IF(ISERROR('Model inputs'!V46<0),'Model inputs'!V46<0,IF('Model inputs'!V46="","",'Model inputs'!V46<0))),'Model inputs'!Z122/-'Model inputs'!V46,"") -> 12.388503 | O19: =IF(IF(IF(ISERROR('Model inputs'!W46<0),'Model inputs'!W46<0,IF('Model inputs'!W46="","",'Model inputs'!W46<0))="",FALSE,IF(ISERROR('Model inputs'!W46<0),'Model inputs'!W46<0,IF('Model inputs'!W46="","",'Model inputs'!W46<0))),'Model inputs'!Z122/-'Model inputs'!W46,"") -> 12.388503 | P19: =IF(IF(IF(ISERROR('Model inputs'!X46<0),'Model inputs'!X46<0,IF('Model inputs'!X46="","",'Model inputs'!X46<0))="",FALSE,IF(ISERROR('Model inputs'!X46<0),'Model inputs'!X46<0,IF('Model inputs'!X46="","",'Model inputs'!X46<0))),'Model inputs'!Z122/-'Model inputs'!X46,"") -> 12.388503 | Q19: =IF(IF(IF(ISERROR('Model inputs'!Y46<0),'Model inputs'!Y46<0,IF('Model inputs'!Y46="","",'Model inputs'!Y46<0))="",FALSE,IF(ISERROR('Model inputs'!Y46<0),'Model inputs'!Y46<0,IF('Model inputs'!Y46="","",'Model inputs'!Y46<0))),'Model inputs'!Z122/-'Model inputs'!Y46,"") -> 12.388503
A20: Lean launch — $5,000 | B20: =0 -> 0 | C20: =IF(IF(IF(ISERROR('Briefcase conversion and cost s'!B77<0),'Briefcase conversion and cost s'!B77<0,IF('Briefcase conversion and cost s'!B77="","",'Briefcase conversion and cost s'!B77<0))="",FALSE,IF(ISERROR('Briefcase conversion and cost s'!B77<0),'Briefcase conversion and cost s'!B77<0,IF('Briefcase conversion and cost s'!B77="","",'Briefcase conversion and cost s'!B77<0))),'Model inputs'!Z123/-'Briefcase conversion and cost s'!B77,"") -> 2.4777007 | D20: =IF(IF(IF(ISERROR('Model inputs'!L46<0),'Model inputs'!L46<0,IF('Model inputs'!L46="","",'Model inputs'!L46<0))="",FALSE,IF(ISERROR('Model inputs'!L46<0),'Model inputs'!L46<0,IF('Model inputs'!L46="","",'Model inputs'!L46<0))),'Model inputs'!Z123/-'Model inputs'!L46,"") -> 2.4777007 | E20: =IF(IF(IF(ISERROR('Model inputs'!M46<0),'Model inputs'!M46<0,IF('Model inputs'!M46="","",'Model inputs'!M46<0))="",FALSE,IF(ISERROR('Model inputs'!M46<0),'Model inputs'!M46<0,IF('Model inputs'!M46="","",'Model inputs'!M46<0))),'Model inputs'!Z123/-'Model inputs'!M46,"") -> 2.4777007 | F20: =IF(IF(IF(ISERROR('Model inputs'!N46<0),'Model inputs'!N46<0,IF('Model inputs'!N46="","",'Model inputs'!N46<0))="",FALSE,IF(ISERROR('Model inputs'!N46<0),'Model inputs'!N46<0,IF('Model inputs'!N46="","",'Model inputs'!N46<0))),'Model inputs'!Z123/-'Model inputs'!N46,"") -> 2.4777007 | G20: =IF(IF(IF(ISERROR('Model inputs'!O46<0),'Model inputs'!O46<0,IF('Model inputs'!O46="","",'Model inputs'!O46<0))="",FALSE,IF(ISERROR('Model inputs'!O46<0),'Model inputs'!O46<0,IF('Model inputs'!O46="","",'Model inputs'!O46<0))),'Model inputs'!Z123/-'Model inputs'!O46,"") -> 2.4777007 | H20: =IF(IF(IF(ISERROR('Model inputs'!P46<0),'Model inputs'!P46<0,IF('Model inputs'!P46="","",'Model inputs'!P46<0))="",FALSE,IF(ISERROR('Model inputs'!P46<0),'Model inputs'!P46<0,IF('Model inputs'!P46="","",'Model inputs'!P46<0))),'Model inputs'!Z123/-'Model inputs'!P46,"") -> 2.4777007 | I20: =IF(IF(IF(ISERROR('Model inputs'!Q46<0),'Model inputs'!Q46<0,IF('Model inputs'!Q46="","",'Model inputs'!Q46<0))="",FALSE,IF(ISERROR('Model inputs'!Q46<0),'Model inputs'!Q46<0,IF('Model inputs'!Q46="","",'Model inputs'!Q46<0))),'Model inputs'!Z123/-'Model inputs'!Q46,"") -> 2.4777007 | J20: =IF(IF(IF(ISERROR('Model inputs'!R46<0),'Model inputs'!R46<0,IF('Model inputs'!R46="","",'Model inputs'!R46<0))="",FALSE,IF(ISERROR('Model inputs'!R46<0),'Model inputs'!R46<0,IF('Model inputs'!R46="","",'Model inputs'!R46<0))),'Model inputs'!Z123/-'Model inputs'!R46,"") -> 2.4777007 | K20: =IF(IF(IF(ISERROR('Model inputs'!S46<0),'Model inputs'!S46<0,IF('Model inputs'!S46="","",'Model inputs'!S46<0))="",FALSE,IF(ISERROR('Model inputs'!S46<0),'Model inputs'!S46<0,IF('Model inputs'!S46="","",'Model inputs'!S46<0))),'Model inputs'!Z123/-'Model inputs'!S46,"") -> 2.4777007 | L20: =IF(IF(IF(ISERROR('Model inputs'!T46<0),'Model inputs'!T46<0,IF('Model inputs'!T46="","",'Model inputs'!T46<0))="",FALSE,IF(ISERROR('Model inputs'!T46<0),'Model inputs'!T46<0,IF('Model inputs'!T46="","",'Model inputs'!T46<0))),'Model inputs'!Z123/-'Model inputs'!T46,"") -> 2.4777007 | M20: =IF(IF(IF(ISERROR('Model inputs'!U46<0),'Model inputs'!U46<0,IF('Model inputs'!U46="","",'Model inputs'!U46<0))="",FALSE,IF(ISERROR('Model inputs'!U46<0),'Model inputs'!U46<0,IF('Model inputs'!U46="","",'Model inputs'!U46<0))),'Model inputs'!Z123/-'Model inputs'!U46,"") -> 2.4777007 | N20: =IF(IF(IF(ISERROR('Model inputs'!V46<0),'Model inputs'!V46<0,IF('Model inputs'!V46="","",'Model inputs'!V46<0))="",FALSE,IF(ISERROR('Model inputs'!V46<0),'Model inputs'!V46<0,IF('Model inputs'!V46="","",'Model inputs'!V46<0))),'Model inputs'!Z123/-'Model inputs'!V46,"") -> 2.4777007 | O20: =IF(IF(IF(ISERROR('Model inputs'!W46<0),'Model inputs'!W46<0,IF('Model inputs'!W46="","",'Model inputs'!W46<0))="",FALSE,IF(ISERROR('Model inputs'!W46<0),'Model inputs'!W46<0,IF('Model inputs'!W46="","",'Model inputs'!W46<0))),'Model inputs'!Z123/-'Model inputs'!W46,"") -> 2.4777007 | P20: =IF(IF(IF(ISERROR('Model inputs'!X46<0),'Model inputs'!X46<0,IF('Model inputs'!X46="","",'Model inputs'!X46<0))="",FALSE,IF(ISERROR('Model inputs'!X46<0),'Model inputs'!X46<0,IF('Model inputs'!X46="","",'Model inputs'!X46<0))),'Model inputs'!Z123/-'Model inputs'!X46,"") -> 2.4777007 | Q20: =IF(IF(IF(ISERROR('Model inputs'!Y46<0),'Model inputs'!Y46<0,IF('Model inputs'!Y46="","",'Model inputs'!Y46<0))="",FALSE,IF(ISERROR('Model inputs'!Y46<0),'Model inputs'!Y46<0,IF('Model inputs'!Y46="","",'Model inputs'!Y46<0))),'Model inputs'!Z123/-'Model inputs'!Y46,"") -> 2.4777007
A21: Monthly burn | B21: 0 | C21: =MAX(0,-'Briefcase conversion and cost s'!B65) -> 0 | D21: =MAX(0,-'Model inputs'!L83) -> 0 | E21: =MAX(0,-'Model inputs'!M83) -> 0 | F21: =MAX(0,-'Model inputs'!N83) -> 0 | G21: =MAX(0,-'Model inputs'!O83) -> 0 | H21: =MAX(0,-'Model inputs'!P83) -> 0 | I21: =MAX(0,-'Model inputs'!Q83) -> 0 | J21: =MAX(0,-'Model inputs'!R83) -> 0 | K21: =MAX(0,-'Model inputs'!S83) -> 0 | ... Q21: =MAX(0,-'Model inputs'!Y83) -> 0
A22: Cash outlook | C22: ="" | D22: ="" | E22: ="" | F22: ="" | G22: ="" | H22: ="" | I22: ="" | J22: ="" | ... Q22: =""
A23: Bootstrapped — $0 | C23: =IF(IF(IF(ISERROR('Briefcase conversion and cost s'!B65>=0),'Briefcase conversion and cost s'!B65>=0,IF('Briefcase conversion and cost s'!B65="","",'Briefcase conversion and cost s'!B65>=0))="",FALSE,IF(ISERROR('Briefcase conversion and cost s'!B65>=0),'Briefcase conversion and cost s'!B65>=0,IF('Briefcase conversion and cost s'!B65="","",'Briefcase conversion and cost s'!B65>=0))),IF(IF(IF(ISERROR('Model inputs'!Z121=0),'Model inputs'!Z121=0,IF('Model inputs'!Z121="","",'Model inputs'!Z121=0))="",FALSE,IF(ISERROR('Model inputs'!Z121=0),'Model inputs'!Z121=0,IF('Model inputs'!Z121="","",'Model inputs'!Z121=0))),"Cash-positive; no launch buffer","Cash-positive within flat forecast"),"Cash-burning; see runway") -> Cash-positive; no launch buffer | D23: =IF(IF(IF(ISERROR('Model inputs'!L83>=0),'Model inputs'!L83>=0,IF('Model inputs'!L83="","",'Model inputs'!L83>=0))="",FALSE,IF(ISERROR('Model inputs'!L83>=0),'Model inputs'!L83>=0,IF('Model inputs'!L83="","",'Model inputs'!L83>=0))),IF(IF(IF(ISERROR('Model inputs'!Z121=0),'Model inputs'!Z121=0,IF('Model inputs'!Z121="","",'Model inputs'!Z121=0))="",FALSE,IF(ISERROR('Model inputs'!Z121=0),'Model inputs'!Z121=0,IF('Model inputs'!Z121="","",'Model inputs'!Z121=0))),"Cash-positive; no launch buffer","Cash-positive within flat forecast"),"Cash-burning; see runway") -> Cash-positive; no launch buffer | E23: =IF(IF(IF(ISERROR('Model inputs'!M83>=0),'Model inputs'!M83>=0,IF('Model inputs'!M83="","",'Model inputs'!M83>=0))="",FALSE,IF(ISERROR('Model inputs'!M83>=0),'Model inputs'!M83>=0,IF('Model inputs'!M83="","",'Model inputs'!M83>=0))),IF(IF(IF(ISERROR('Model inputs'!Z121=0),'Model inputs'!Z121=0,IF('Model inputs'!Z121="","",'Model inputs'!Z121=0))="",FALSE,IF(ISERROR('Model inputs'!Z121=0),'Model inputs'!Z121=0,IF('Model inputs'!Z121="","",'Model inputs'!Z121=0))),"Cash-positive; no launch buffer","Cash-positive within flat forecast"),"Cash-burning; see runway") -> Cash-positive; no launch buffer | F23: =IF(IF(IF(ISERROR('Model inputs'!N83>=0),'Model inputs'!N83>=0,IF('Model inputs'!N83="","",'Model inputs'!N83>=0))="",FALSE,IF(ISERROR('Model inputs'!N83>=0),'Model inputs'!N83>=0,IF('Model inputs'!N83="","",'Model inputs'!N83>=0))),IF(IF(IF(ISERROR('Model inputs'!Z121=0),'Model inputs'!Z121=0,IF('Model inputs'!Z121="","",'Model inputs'!Z121=0))="",FALSE,IF(ISERROR('Model inputs'!Z121=0),'Model inputs'!Z121=0,IF('Model inputs'!Z121="","",'Model inputs'!Z121=0))),"Cash-positive; no launch buffer","Cash-positive within flat forecast"),"Cash-burning; see runway") -> Cash-positive; no launch buffer | G23: =IF(IF(IF(ISERROR('Model inputs'!O83>=0),'Model inputs'!O83>=0,IF('Model inputs'!O83="","",'Model inputs'!O83>=0))="",FALSE,IF(ISERROR('Model inputs'!O83>=0),'Model inputs'!O83>=0,IF('Model inputs'!O83="","",'Model inputs'!O83>=0))),IF(IF(IF(ISERROR('Model inputs'!Z121=0),'Model inputs'!Z121=0,IF('Model inputs'!Z121="","",'Model inputs'!Z121=0))="",FALSE,IF(ISERROR('Model inputs'!Z121=0),'Model inputs'!Z121=0,IF('Model inputs'!Z121="","",'Model inputs'!Z121=0))),"Cash-positive; no launch buffer","Cash-positive within flat forecast"),"Cash-burning; see runway") -> Cash-positive; no launch buffer | H23: =IF(IF(IF(ISERROR('Model inputs'!P83>=0),'Model inputs'!P83>=0,IF('Model inputs'!P83="","",'Model inputs'!P83>=0))="",FALSE,IF(ISERROR('Model inputs'!P83>=0),'Model inputs'!P83>=0,IF('Model inputs'!P83="","",'Model inputs'!P83>=0))),IF(IF(IF(ISERROR('Model inputs'!Z121=0),'Model inputs'!Z121=0,IF('Model inputs'!Z121="","",'Model inputs'!Z121=0))="",FALSE,IF(ISERROR('Model inputs'!Z121=0),'Model inputs'!Z121=0,IF('Model inputs'!Z121="","",'Model inputs'!Z121=0))),"Cash-positive; no launch buffer","Cash-positive within flat forecast"),"Cash-burning; see runway") -> Cash-positive; no launch buffer | I23: =IF(IF(IF(ISERROR('Model inputs'!Q83>=0),'Model inputs'!Q83>=0,IF('Model inputs'!Q83="","",'Model inputs'!Q83>=0))="",FALSE,IF(ISERROR('Model inputs'!Q83>=0),'Model inputs'!Q83>=0,IF('Model inputs'!Q83="","",'Model inputs'!Q83>=0))),IF(IF(IF(ISERROR('Model inputs'!Z121=0),'Model inputs'!Z121=0,IF('Model inputs'!Z121="","",'Model inputs'!Z121=0))="",FALSE,IF(ISERROR('Model inputs'!Z121=0),'Model inputs'!Z121=0,IF('Model inputs'!Z121="","",'Model inputs'!Z121=0))),"Cash-positive; no launch buffer","Cash-positive within flat forecast"),"Cash-burning; see runway") -> Cash-positive; no launch buffer | J23: =IF(IF(IF(ISERROR('Model inputs'!R83>=0),'Model inputs'!R83>=0,IF('Model inputs'!R83="","",'Model inputs'!R83>=0))="",FALSE,IF(ISERROR('Model inputs'!R83>=0),'Model inputs'!R83>=0,IF('Model inputs'!R83="","",'Model inputs'!R83>=0))),IF(IF(IF(ISERROR('Model inputs'!Z121=0),'Model inputs'!Z121=0,IF('Model inputs'!Z121="","",'Model inputs'!Z121=0))="",FALSE,IF(ISERROR('Model inputs'!Z121=0),'Model inputs'!Z121=0,IF('Model inputs'!Z121="","",'Model inputs'!Z121=0))),"Cash-positive; no launch buffer","Cash-positive within flat forecast"),"Cash-burning; see runway") -> Cash-positive; no launch buffer | K23: =IF(IF(IF(ISERROR('Model inputs'!S83>=0),'Model inputs'!S83>=0,IF('Model inputs'!S83="","",'Model inputs'!S83>=0))="",FALSE,IF(ISERROR('Model inputs'!S83>=0),'Model inputs'!S83>=0,IF('Model inputs'!S83="","",'Model inputs'!S83>=0))),IF(IF(IF(ISERROR('Model inputs'!Z121=0),'Model inputs'!Z121=0,IF('Model inputs'!Z121="","",'Model inputs'!Z121=0))="",FALSE,IF(ISERROR('Model inputs'!Z121=0),'Model inputs'!Z121=0,IF('Model inputs'!Z121="","",'Model inputs'!Z121=0))),"Cash-positive; no launch buffer","Cash-positive within flat forecast"),"Cash-burning; see runway") -> Cash-positive; no launch buffer | L23: =IF(IF(IF(ISERROR('Model inputs'!T83>=0),'Model inputs'!T83>=0,IF('Model inputs'!T83="","",'Model inputs'!T83>=0))="",FALSE,IF(ISERROR('Model inputs'!T83>=0),'Model inputs'!T83>=0,IF('Model inputs'!T83="","",'Model inputs'!T83>=0))),IF(IF(IF(ISERROR('Model inputs'!Z121=0),'Model inputs'!Z121=0,IF('Model inputs'!Z121="","",'Model inputs'!Z121=0))="",FALSE,IF(ISERROR('Model inputs'!Z121=0),'Model inputs'!Z121=0,IF('Model inputs'!Z121="","",'Model inputs'!Z121=0))),"Cash-positive; no launch buffer","Cash-positive within flat forecast"),"Cash-burning; see runway") -> Cash-positive; no launch buffer | M23: =IF(IF(IF(ISERROR('Model inputs'!U83>=0),'Model inputs'!U83>=0,IF('Model inputs'!U83="","",'Model inputs'!U83>=0))="",FALSE,IF(ISERROR('Model inputs'!U83>=0),'Model inputs'!U83>=0,IF('Model inputs'!U83="","",'Model inputs'!U83>=0))),IF(IF(IF(ISERROR('Model inputs'!Z121=0),'Model inputs'!Z121=0,IF('Model inputs'!Z121="","",'Model inputs'!Z121=0))="",FALSE,IF(ISERROR('Model inputs'!Z121=0),'Model inputs'!Z121=0,IF('Model inputs'!Z121="","",'Model inputs'!Z121=0))),"Cash-positive; no launch buffer","Cash-positive within flat forecast"),"Cash-burning; see runway") -> Cash-positive; no launch buffer | N23: =IF(IF(IF(ISERROR('Model inputs'!V83>=0),'Model inputs'!V83>=0,IF('Model inputs'!V83="","",'Model inputs'!V83>=0))="",FALSE,IF(ISERROR('Model inputs'!V83>=0),'Model inputs'!V83>=0,IF('Model inputs'!V83="","",'Model inputs'!V83>=0))),IF(IF(IF(ISERROR('Model inputs'!Z121=0),'Model inputs'!Z121=0,IF('Model inputs'!Z121="","",'Model inputs'!Z121=0))="",FALSE,IF(ISERROR('Model inputs'!Z121=0),'Model inputs'!Z121=0,IF('Model inputs'!Z121="","",'Model inputs'!Z121=0))),"Cash-positive; no launch buffer","Cash-positive within flat forecast"),"Cash-burning; see runway") -> Cash-positive; no launch buffer | O23: =IF(IF(IF(ISERROR('Model inputs'!W83>=0),'Model inputs'!W83>=0,IF('Model inputs'!W83="","",'Model inputs'!W83>=0))="",FALSE,IF(ISERROR('Model inputs'!W83>=0),'Model inputs'!W83>=0,IF('Model inputs'!W83="","",'Model inputs'!W83>=0))),IF(IF(IF(ISERROR('Model inputs'!Z121=0),'Model inputs'!Z121=0,IF('Model inputs'!Z121="","",'Model inputs'!Z121=0))="",FALSE,IF(ISERROR('Model inputs'!Z121=0),'Model inputs'!Z121=0,IF('Model inputs'!Z121="","",'Model inputs'!Z121=0))),"Cash-positive; no launch buffer","Cash-positive within flat forecast"),"Cash-burning; see runway") -> Cash-positive; no launch buffer | P23: =IF(IF(IF(ISERROR('Model inputs'!X83>=0),'Model inputs'!X83>=0,IF('Model inputs'!X83="","",'Model inputs'!X83>=0))="",FALSE,IF(ISERROR('Model inputs'!X83>=0),'Model inputs'!X83>=0,IF('Model inputs'!X83="","",'Model inputs'!X83>=0))),IF(IF(IF(ISERROR('Model inputs'!Z121=0),'Model inputs'!Z121=0,IF('Model inputs'!Z121="","",'Model inputs'!Z121=0))="",FALSE,IF(ISERROR('Model inputs'!Z121=0),'Model inputs'!Z121=0,IF('Model inputs'!Z121="","",'Model inputs'!Z121=0))),"Cash-positive; no launch buffer","Cash-positive within flat forecast"),"Cash-burning; see runway") -> Cash-positive; no launch buffer | Q23: =IF(IF(IF(ISERROR('Model inputs'!Y83>=0),'Model inputs'!Y83>=0,IF('Model inputs'!Y83="","",'Model inputs'!Y83>=0))="",FALSE,IF(ISERROR('Model inputs'!Y83>=0),'Model inputs'!Y83>=0,IF('Model inputs'!Y83="","",'Model inputs'!Y83>=0))),IF(IF(IF(ISERROR('Model inputs'!Z121=0),'Model inputs'!Z121=0,IF('Model inputs'!Z121="","",'Model inputs'!Z121=0))="",FALSE,IF(ISERROR('Model inputs'!Z121=0),'Model inputs'!Z121=0,IF('Model inputs'!Z121="","",'Model inputs'!Z121=0))),"Cash-positive; no launch buffer","Cash-positive within flat forecast"),"Cash-burning; see runway") -> Cash-positive; no launch buffer
A24: Illustrative pre-seed — $25,000 | C24: =IF(IF(IF(ISERROR('Briefcase conversion and cost s'!B65>=0),'Briefcase conversion and cost s'!B65>=0,IF('Briefcase conversion and cost s'!B65="","",'Briefcase conversion and cost s'!B65>=0))="",FALSE,IF(ISERROR('Briefcase conversion and cost s'!B65>=0),'Briefcase conversion and cost s'!B65>=0,IF('Briefcase conversion and cost s'!B65="","",'Briefcase conversion and cost s'!B65>=0))),IF(IF(IF(ISERROR('Model inputs'!Z122=0),'Model inputs'!Z122=0,IF('Model inputs'!Z122="","",'Model inputs'!Z122=0))="",FALSE,IF(ISERROR('Model inputs'!Z122=0),'Model inputs'!Z122=0,IF('Model inputs'!Z122="","",'Model inputs'!Z122=0))),"Cash-positive; no launch buffer","Cash-positive within flat forecast"),"Cash-burning; see runway") -> Cash-positive within flat forecast | D24: =IF(IF(IF(ISERROR('Model inputs'!L83>=0),'Model inputs'!L83>=0,IF('Model inputs'!L83="","",'Model inputs'!L83>=0))="",FALSE,IF(ISERROR('Model inputs'!L83>=0),'Model inputs'!L83>=0,IF('Model inputs'!L83="","",'Model inputs'!L83>=0))),IF(IF(IF(ISERROR('Model inputs'!Z122=0),'Model inputs'!Z122=0,IF('Model inputs'!Z122="","",'Model inputs'!Z122=0))="",FALSE,IF(ISERROR('Model inputs'!Z122=0),'Model inputs'!Z122=0,IF('Model inputs'!Z122="","",'Model inputs'!Z122=0))),"Cash-positive; no launch buffer","Cash-positive within flat forecast"),"Cash-burning; see runway") -> Cash-positive within flat forecast | E24: =IF(IF(IF(ISERROR('Model inputs'!M83>=0),'Model inputs'!M83>=0,IF('Model inputs'!M83="","",'Model inputs'!M83>=0))="",FALSE,IF(ISERROR('Model inputs'!M83>=0),'Model inputs'!M83>=0,IF('Model inputs'!M83="","",'Model inputs'!M83>=0))),IF(IF(IF(ISERROR('Model inputs'!Z122=0),'Model inputs'!Z122=0,IF('Model inputs'!Z122="","",'Model inputs'!Z122=0))="",FALSE,IF(ISERROR('Model inputs'!Z122=0),'Model inputs'!Z122=0,IF('Model inputs'!Z122="","",'Model inputs'!Z122=0))),"Cash-positive; no launch buffer","Cash-positive within flat forecast"),"Cash-burning; see runway") -> Cash-positive within flat forecast | F24: =IF(IF(IF(ISERROR('Model inputs'!N83>=0),'Model inputs'!N83>=0,IF('Model inputs'!N83="","",'Model inputs'!N83>=0))="",FALSE,IF(ISERROR('Model inputs'!N83>=0),'Model inputs'!N83>=0,IF('Model inputs'!N83="","",'Model inputs'!N83>=0))),IF(IF(IF(ISERROR('Model inputs'!Z122=0),'Model inputs'!Z122=0,IF('Model inputs'!Z122="","",'Model inputs'!Z122=0))="",FALSE,IF(ISERROR('Model inputs'!Z122=0),'Model inputs'!Z122=0,IF('Model inputs'!Z122="","",'Model inputs'!Z122=0))),"Cash-positive; no launch buffer","Cash-positive within flat forecast"),"Cash-burning; see runway") -> Cash-positive within flat forecast | G24: =IF(IF(IF(ISERROR('Model inputs'!O83>=0),'Model inputs'!O83>=0,IF('Model inputs'!O83="","",'Model inputs'!O83>=0))="",FALSE,IF(ISERROR('Model inputs'!O83>=0),'Model inputs'!O83>=0,IF('Model inputs'!O83="","",'Model inputs'!O83>=0))),IF(IF(IF(ISERROR('Model inputs'!Z122=0),'Model inputs'!Z122=0,IF('Model inputs'!Z122="","",'Model inputs'!Z122=0))="",FALSE,IF(ISERROR('Model inputs'!Z122=0),'Model inputs'!Z122=0,IF('Model inputs'!Z122="","",'Model inputs'!Z122=0))),"Cash-positive; no launch buffer","Cash-positive within flat forecast"),"Cash-burning; see runway") -> Cash-positive within flat forecast | H24: =IF(IF(IF(ISERROR('Model inputs'!P83>=0),'Model inputs'!P83>=0,IF('Model inputs'!P83="","",'Model inputs'!P83>=0))="",FALSE,IF(ISERROR('Model inputs'!P83>=0),'Model inputs'!P83>=0,IF('Model inputs'!P83="","",'Model inputs'!P83>=0))),IF(IF(IF(ISERROR('Model inputs'!Z122=0),'Model inputs'!Z122=0,IF('Model inputs'!Z122="","",'Model inputs'!Z122=0))="",FALSE,IF(ISERROR('Model inputs'!Z122=0),'Model inputs'!Z122=0,IF('Model inputs'!Z122="","",'Model inputs'!Z122=0))),"Cash-positive; no launch buffer","Cash-positive within flat forecast"),"Cash-burning; see runway") -> Cash-positive within flat forecast | I24: =IF(IF(IF(ISERROR('Model inputs'!Q83>=0),'Model inputs'!Q83>=0,IF('Model inputs'!Q83="","",'Model inputs'!Q83>=0))="",FALSE,IF(ISERROR('Model inputs'!Q83>=0),'Model inputs'!Q83>=0,IF('Model inputs'!Q83="","",'Model inputs'!Q83>=0))),IF(IF(IF(ISERROR('Model inputs'!Z122=0),'Model inputs'!Z122=0,IF('Model inputs'!Z122="","",'Model inputs'!Z122=0))="",FALSE,IF(ISERROR('Model inputs'!Z122=0),'Model inputs'!Z122=0,IF('Model inputs'!Z122="","",'Model inputs'!Z122=0))),"Cash-positive; no launch buffer","Cash-positive within flat forecast"),"Cash-burning; see runway") -> Cash-positive within flat forecast | J24: =IF(IF(IF(ISERROR('Model inputs'!R83>=0),'Model inputs'!R83>=0,IF('Model inputs'!R83="","",'Model inputs'!R83>=0))="",FALSE,IF(ISERROR('Model inputs'!R83>=0),'Model inputs'!R83>=0,IF('Model inputs'!R83="","",'Model inputs'!R83>=0))),IF(IF(IF(ISERROR('Model inputs'!Z122=0),'Model inputs'!Z122=0,IF('Model inputs'!Z122="","",'Model inputs'!Z122=0))="",FALSE,IF(ISERROR('Model inputs'!Z122=0),'Model inputs'!Z122=0,IF('Model inputs'!Z122="","",'Model inputs'!Z122=0))),"Cash-positive; no launch buffer","Cash-positive within flat forecast"),"Cash-burning; see runway") -> Cash-positive within flat forecast | K24: =IF(IF(IF(ISERROR('Model inputs'!S83>=0),'Model inputs'!S83>=0,IF('Model inputs'!S83="","",'Model inputs'!S83>=0))="",FALSE,IF(ISERROR('Model inputs'!S83>=0),'Model inputs'!S83>=0,IF('Model inputs'!S83="","",'Model inputs'!S83>=0))),IF(IF(IF(ISERROR('Model inputs'!Z122=0),'Model inputs'!Z122=0,IF('Model inputs'!Z122="","",'Model inputs'!Z122=0))="",FALSE,IF(ISERROR('Model inputs'!Z122=0),'Model inputs'!Z122=0,IF('Model inputs'!Z122="","",'Model inputs'!Z122=0))),"Cash-positive; no launch buffer","Cash-positive within flat forecast"),"Cash-burning; see runway") -> Cash-positive within flat forecast | L24: =IF(IF(IF(ISERROR('Model inputs'!T83>=0),'Model inputs'!T83>=0,IF('Model inputs'!T83="","",'Model inputs'!T83>=0))="",FALSE,IF(ISERROR('Model inputs'!T83>=0),'Model inputs'!T83>=0,IF('Model inputs'!T83="","",'Model inputs'!T83>=0))),IF(IF(IF(ISERROR('Model inputs'!Z122=0),'Model inputs'!Z122=0,IF('Model inputs'!Z122="","",'Model inputs'!Z122=0))="",FALSE,IF(ISERROR('Model inputs'!Z122=0),'Model inputs'!Z122=0,IF('Model inputs'!Z122="","",'Model inputs'!Z122=0))),"Cash-positive; no launch buffer","Cash-positive within flat forecast"),"Cash-burning; see runway") -> Cash-positive within flat forecast | M24: =IF(IF(IF(ISERROR('Model inputs'!U83>=0),'Model inputs'!U83>=0,IF('Model inputs'!U83="","",'Model inputs'!U83>=0))="",FALSE,IF(ISERROR('Model inputs'!U83>=0),'Model inputs'!U83>=0,IF('Model inputs'!U83="","",'Model inputs'!U83>=0))),IF(IF(IF(ISERROR('Model inputs'!Z122=0),'Model inputs'!Z122=0,IF('Model inputs'!Z122="","",'Model inputs'!Z122=0))="",FALSE,IF(ISERROR('Model inputs'!Z122=0),'Model inputs'!Z122=0,IF('Model inputs'!Z122="","",'Model inputs'!Z122=0))),"Cash-positive; no launch buffer","Cash-positive within flat forecast"),"Cash-burning; see runway") -> Cash-positive within flat forecast | N24: =IF(IF(IF(ISERROR('Model inputs'!V83>=0),'Model inputs'!V83>=0,IF('Model inputs'!V83="","",'Model inputs'!V83>=0))="",FALSE,IF(ISERROR('Model inputs'!V83>=0),'Model inputs'!V83>=0,IF('Model inputs'!V83="","",'Model inputs'!V83>=0))),IF(IF(IF(ISERROR('Model inputs'!Z122=0),'Model inputs'!Z122=0,IF('Model inputs'!Z122="","",'Model inputs'!Z122=0))="",FALSE,IF(ISERROR('Model inputs'!Z122=0),'Model inputs'!Z122=0,IF('Model inputs'!Z122="","",'Model inputs'!Z122=0))),"Cash-positive; no launch buffer","Cash-positive within flat forecast"),"Cash-burning; see runway") -> Cash-positive within flat forecast | O24: =IF(IF(IF(ISERROR('Model inputs'!W83>=0),'Model inputs'!W83>=0,IF('Model inputs'!W83="","",'Model inputs'!W83>=0))="",FALSE,IF(ISERROR('Model inputs'!W83>=0),'Model inputs'!W83>=0,IF('Model inputs'!W83="","",'Model inputs'!W83>=0))),IF(IF(IF(ISERROR('Model inputs'!Z122=0),'Model inputs'!Z122=0,IF('Model inputs'!Z122="","",'Model inputs'!Z122=0))="",FALSE,IF(ISERROR('Model inputs'!Z122=0),'Model inputs'!Z122=0,IF('Model inputs'!Z122="","",'Model inputs'!Z122=0))),"Cash-positive; no launch buffer","Cash-positive within flat forecast"),"Cash-burning; see runway") -> Cash-positive within flat forecast | P24: =IF(IF(IF(ISERROR('Model inputs'!X83>=0),'Model inputs'!X83>=0,IF('Model inputs'!X83="","",'Model inputs'!X83>=0))="",FALSE,IF(ISERROR('Model inputs'!X83>=0),'Model inputs'!X83>=0,IF('Model inputs'!X83="","",'Model inputs'!X83>=0))),IF(IF(IF(ISERROR('Model inputs'!Z122=0),'Model inputs'!Z122=0,IF('Model inputs'!Z122="","",'Model inputs'!Z122=0))="",FALSE,IF(ISERROR('Model inputs'!Z122=0),'Model inputs'!Z122=0,IF('Model inputs'!Z122="","",'Model inputs'!Z122=0))),"Cash-positive; no launch buffer","Cash-positive within flat forecast"),"Cash-burning; see runway") -> Cash-positive within flat forecast | Q24: =IF(IF(IF(ISERROR('Model inputs'!Y83>=0),'Model inputs'!Y83>=0,IF('Model inputs'!Y83="","",'Model inputs'!Y83>=0))="",FALSE,IF(ISERROR('Model inputs'!Y83>=0),'Model inputs'!Y83>=0,IF('Model inputs'!Y83="","",'Model inputs'!Y83>=0))),IF(IF(IF(ISERROR('Model inputs'!Z122=0),'Model inputs'!Z122=0,IF('Model inputs'!Z122="","",'Model inputs'!Z122=0))="",FALSE,IF(ISERROR('Model inputs'!Z122=0),'Model inputs'!Z122=0,IF('Model inputs'!Z122="","",'Model inputs'!Z122=0))),"Cash-positive; no launch buffer","Cash-positive within flat forecast"),"Cash-burning; see runway") -> Cash-positive within flat forecast
A25: Lean launch — $5,000 | C25: =IF(IF(IF(ISERROR('Briefcase conversion and cost s'!B65>=0),'Briefcase conversion and cost s'!B65>=0,IF('Briefcase conversion and cost s'!B65="","",'Briefcase conversion and cost s'!B65>=0))="",FALSE,IF(ISERROR('Briefcase conversion and cost s'!B65>=0),'Briefcase conversion and cost s'!B65>=0,IF('Briefcase conversion and cost s'!B65="","",'Briefcase conversion and cost s'!B65>=0))),IF(IF(IF(ISERROR('Model inputs'!Z123=0),'Model inputs'!Z123=0,IF('Model inputs'!Z123="","",'Model inputs'!Z123=0))="",FALSE,IF(ISERROR('Model inputs'!Z123=0),'Model inputs'!Z123=0,IF('Model inputs'!Z123="","",'Model inputs'!Z123=0))),"Cash-positive; no launch buffer","Cash-positive within flat forecast"),"Cash-burning; see runway") -> Cash-positive within flat forecast | D25: =IF(IF(IF(ISERROR('Model inputs'!L83>=0),'Model inputs'!L83>=0,IF('Model inputs'!L83="","",'Model inputs'!L83>=0))="",FALSE,IF(ISERROR('Model inputs'!L83>=0),'Model inputs'!L83>=0,IF('Model inputs'!L83="","",'Model inputs'!L83>=0))),IF(IF(IF(ISERROR('Model inputs'!Z123=0),'Model inputs'!Z123=0,IF('Model inputs'!Z123="","",'Model inputs'!Z123=0))="",FALSE,IF(ISERROR('Model inputs'!Z123=0),'Model inputs'!Z123=0,IF('Model inputs'!Z123="","",'Model inputs'!Z123=0))),"Cash-positive; no launch buffer","Cash-positive within flat forecast"),"Cash-burning; see runway") -> Cash-positive within flat forecast | E25: =IF(IF(IF(ISERROR('Model inputs'!M83>=0),'Model inputs'!M83>=0,IF('Model inputs'!M83="","",'Model inputs'!M83>=0))="",FALSE,IF(ISERROR('Model inputs'!M83>=0),'Model inputs'!M83>=0,IF('Model inputs'!M83="","",'Model inputs'!M83>=0))),IF(IF(IF(ISERROR('Model inputs'!Z123=0),'Model inputs'!Z123=0,IF('Model inputs'!Z123="","",'Model inputs'!Z123=0))="",FALSE,IF(ISERROR('Model inputs'!Z123=0),'Model inputs'!Z123=0,IF('Model inputs'!Z123="","",'Model inputs'!Z123=0))),"Cash-positive; no launch buffer","Cash-positive within flat forecast"),"Cash-burning; see runway") -> Cash-positive within flat forecast | F25: =IF(IF(IF(ISERROR('Model inputs'!N83>=0),'Model inputs'!N83>=0,IF('Model inputs'!N83="","",'Model inputs'!N83>=0))="",FALSE,IF(ISERROR('Model inputs'!N83>=0),'Model inputs'!N83>=0,IF('Model inputs'!N83="","",'Model inputs'!N83>=0))),IF(IF(IF(ISERROR('Model inputs'!Z123=0),'Model inputs'!Z123=0,IF('Model inputs'!Z123="","",'Model inputs'!Z123=0))="",FALSE,IF(ISERROR('Model inputs'!Z123=0),'Model inputs'!Z123=0,IF('Model inputs'!Z123="","",'Model inputs'!Z123=0))),"Cash-positive; no launch buffer","Cash-positive within flat forecast"),"Cash-burning; see runway") -> Cash-positive within flat forecast | G25: =IF(IF(IF(ISERROR('Model inputs'!O83>=0),'Model inputs'!O83>=0,IF('Model inputs'!O83="","",'Model inputs'!O83>=0))="",FALSE,IF(ISERROR('Model inputs'!O83>=0),'Model inputs'!O83>=0,IF('Model inputs'!O83="","",'Model inputs'!O83>=0))),IF(IF(IF(ISERROR('Model inputs'!Z123=0),'Model inputs'!Z123=0,IF('Model inputs'!Z123="","",'Model inputs'!Z123=0))="",FALSE,IF(ISERROR('Model inputs'!Z123=0),'Model inputs'!Z123=0,IF('Model inputs'!Z123="","",'Model inputs'!Z123=0))),"Cash-positive; no launch buffer","Cash-positive within flat forecast"),"Cash-burning; see runway") -> Cash-positive within flat forecast | H25: =IF(IF(IF(ISERROR('Model inputs'!P83>=0),'Model inputs'!P83>=0,IF('Model inputs'!P83="","",'Model inputs'!P83>=0))="",FALSE,IF(ISERROR('Model inputs'!P83>=0),'Model inputs'!P83>=0,IF('Model inputs'!P83="","",'Model inputs'!P83>=0))),IF(IF(IF(ISERROR('Model inputs'!Z123=0),'Model inputs'!Z123=0,IF('Model inputs'!Z123="","",'Model inputs'!Z123=0))="",FALSE,IF(ISERROR('Model inputs'!Z123=0),'Model inputs'!Z123=0,IF('Model inputs'!Z123="","",'Model inputs'!Z123=0))),"Cash-positive; no launch buffer","Cash-positive within flat forecast"),"Cash-burning; see runway") -> Cash-positive within flat forecast | I25: =IF(IF(IF(ISERROR('Model inputs'!Q83>=0),'Model inputs'!Q83>=0,IF('Model inputs'!Q83="","",'Model inputs'!Q83>=0))="",FALSE,IF(ISERROR('Model inputs'!Q83>=0),'Model inputs'!Q83>=0,IF('Model inputs'!Q83="","",'Model inputs'!Q83>=0))),IF(IF(IF(ISERROR('Model inputs'!Z123=0),'Model inputs'!Z123=0,IF('Model inputs'!Z123="","",'Model inputs'!Z123=0))="",FALSE,IF(ISERROR('Model inputs'!Z123=0),'Model inputs'!Z123=0,IF('Model inputs'!Z123="","",'Model inputs'!Z123=0))),"Cash-positive; no launch buffer","Cash-positive within flat forecast"),"Cash-burning; see runway") -> Cash-positive within flat forecast | J25: =IF(IF(IF(ISERROR('Model inputs'!R83>=0),'Model inputs'!R83>=0,IF('Model inputs'!R83="","",'Model inputs'!R83>=0))="",FALSE,IF(ISERROR('Model inputs'!R83>=0),'Model inputs'!R83>=0,IF('Model inputs'!R83="","",'Model inputs'!R83>=0))),IF(IF(IF(ISERROR('Model inputs'!Z123=0),'Model inputs'!Z123=0,IF('Model inputs'!Z123="","",'Model inputs'!Z123=0))="",FALSE,IF(ISERROR('Model inputs'!Z123=0),'Model inputs'!Z123=0,IF('Model inputs'!Z123="","",'Model inputs'!Z123=0))),"Cash-positive; no launch buffer","Cash-positive within flat forecast"),"Cash-burning; see runway") -> Cash-positive within flat forecast | K25: =IF(IF(IF(ISERROR('Model inputs'!S83>=0),'Model inputs'!S83>=0,IF('Model inputs'!S83="","",'Model inputs'!S83>=0))="",FALSE,IF(ISERROR('Model inputs'!S83>=0),'Model inputs'!S83>=0,IF('Model inputs'!S83="","",'Model inputs'!S83>=0))),IF(IF(IF(ISERROR('Model inputs'!Z123=0),'Model inputs'!Z123=0,IF('Model inputs'!Z123="","",'Model inputs'!Z123=0))="",FALSE,IF(ISERROR('Model inputs'!Z123=0),'Model inputs'!Z123=0,IF('Model inputs'!Z123="","",'Model inputs'!Z123=0))),"Cash-positive; no launch buffer","Cash-positive within flat forecast"),"Cash-burning; see runway") -> Cash-positive within flat forecast | L25: =IF(IF(IF(ISERROR('Model inputs'!T83>=0),'Model inputs'!T83>=0,IF('Model inputs'!T83="","",'Model inputs'!T83>=0))="",FALSE,IF(ISERROR('Model inputs'!T83>=0),'Model inputs'!T83>=0,IF('Model inputs'!T83="","",'Model inputs'!T83>=0))),IF(IF(IF(ISERROR('Model inputs'!Z123=0),'Model inputs'!Z123=0,IF('Model inputs'!Z123="","",'Model inputs'!Z123=0))="",FALSE,IF(ISERROR('Model inputs'!Z123=0),'Model inputs'!Z123=0,IF('Model inputs'!Z123="","",'Model inputs'!Z123=0))),"Cash-positive; no launch buffer","Cash-positive within flat forecast"),"Cash-burning; see runway") -> Cash-positive within flat forecast | M25: =IF(IF(IF(ISERROR('Model inputs'!U83>=0),'Model inputs'!U83>=0,IF('Model inputs'!U83="","",'Model inputs'!U83>=0))="",FALSE,IF(ISERROR('Model inputs'!U83>=0),'Model inputs'!U83>=0,IF('Model inputs'!U83="","",'Model inputs'!U83>=0))),IF(IF(IF(ISERROR('Model inputs'!Z123=0),'Model inputs'!Z123=0,IF('Model inputs'!Z123="","",'Model inputs'!Z123=0))="",FALSE,IF(ISERROR('Model inputs'!Z123=0),'Model inputs'!Z123=0,IF('Model inputs'!Z123="","",'Model inputs'!Z123=0))),"Cash-positive; no launch buffer","Cash-positive within flat forecast"),"Cash-burning; see runway") -> Cash-positive within flat forecast | N25: =IF(IF(IF(ISERROR('Model inputs'!V83>=0),'Model inputs'!V83>=0,IF('Model inputs'!V83="","",'Model inputs'!V83>=0))="",FALSE,IF(ISERROR('Model inputs'!V83>=0),'Model inputs'!V83>=0,IF('Model inputs'!V83="","",'Model inputs'!V83>=0))),IF(IF(IF(ISERROR('Model inputs'!Z123=0),'Model inputs'!Z123=0,IF('Model inputs'!Z123="","",'Model inputs'!Z123=0))="",FALSE,IF(ISERROR('Model inputs'!Z123=0),'Model inputs'!Z123=0,IF('Model inputs'!Z123="","",'Model inputs'!Z123=0))),"Cash-positive; no launch buffer","Cash-positive within flat forecast"),"Cash-burning; see runway") -> Cash-positive within flat forecast | O25: =IF(IF(IF(ISERROR('Model inputs'!W83>=0),'Model inputs'!W83>=0,IF('Model inputs'!W83="","",'Model inputs'!W83>=0))="",FALSE,IF(ISERROR('Model inputs'!W83>=0),'Model inputs'!W83>=0,IF('Model inputs'!W83="","",'Model inputs'!W83>=0))),IF(IF(IF(ISERROR('Model inputs'!Z123=0),'Model inputs'!Z123=0,IF('Model inputs'!Z123="","",'Model inputs'!Z123=0))="",FALSE,IF(ISERROR('Model inputs'!Z123=0),'Model inputs'!Z123=0,IF('Model inputs'!Z123="","",'Model inputs'!Z123=0))),"Cash-positive; no launch buffer","Cash-positive within flat forecast"),"Cash-burning; see runway") -> Cash-positive within flat forecast | P25: =IF(IF(IF(ISERROR('Model inputs'!X83>=0),'Model inputs'!X83>=0,IF('Model inputs'!X83="","",'Model inputs'!X83>=0))="",FALSE,IF(ISERROR('Model inputs'!X83>=0),'Model inputs'!X83>=0,IF('Model inputs'!X83="","",'Model inputs'!X83>=0))),IF(IF(IF(ISERROR('Model inputs'!Z123=0),'Model inputs'!Z123=0,IF('Model inputs'!Z123="","",'Model inputs'!Z123=0))="",FALSE,IF(ISERROR('Model inputs'!Z123=0),'Model inputs'!Z123=0,IF('Model inputs'!Z123="","",'Model inputs'!Z123=0))),"Cash-positive; no launch buffer","Cash-positive within flat forecast"),"Cash-burning; see runway") -> Cash-positive within flat forecast | Q25: =IF(IF(IF(ISERROR('Model inputs'!Y83>=0),'Model inputs'!Y83>=0,IF('Model inputs'!Y83="","",'Model inputs'!Y83>=0))="",FALSE,IF(ISERROR('Model inputs'!Y83>=0),'Model inputs'!Y83>=0,IF('Model inputs'!Y83="","",'Model inputs'!Y83>=0))),IF(IF(IF(ISERROR('Model inputs'!Z123=0),'Model inputs'!Z123=0,IF('Model inputs'!Z123="","",'Model inputs'!Z123=0))="",FALSE,IF(ISERROR('Model inputs'!Z123=0),'Model inputs'!Z123=0,IF('Model inputs'!Z123="","",'Model inputs'!Z123=0))),"Cash-positive; no launch buffer","Cash-positive within flat forecast"),"Cash-burning; see runway") -> Cash-positive within flat forecast

Sheet Briefcase conversion and cost s
A1: Briefcase conversion and cost sensitivities
A2: Briefcase — Runway & decisions · Briefcase Base
A4: Variable / dimension | B4: 2026-10
A5: Pro subscribers | B5: ='Model inputs'!Z22*'Model inputs'!Z34 -> 120
A6: Pro subscribers > Briefcase Conservative | B6: ='Model inputs'!Z30*'Model inputs'!Z42 -> 40
A7: Pro subscribers > Briefcase Conservative — doubled Crustdata | B7: ='Model inputs'!Z23*'Model inputs'!Z35 -> 40
A8: Pro subscribers > Briefcase Conservative — 5% conversion | B8: ='Model inputs'!Z29*'Model inputs'!Z41 -> 20
A9: Pro subscribers > Briefcase Conservative — 5% conversion — doubled Crustdata | B9: ='Model inputs'!Z25*'Model inputs'!Z37 -> 20
A10: Pro subscribers > Briefcase Base — doubled Crustdata | B10: ='Model inputs'!Z33*'Model inputs'!Z45 -> 120
A11: Pro subscribers > Briefcase Base — 5% conversion | B11: ='Model inputs'!Z31*'Model inputs'!Z43 -> 60
A12: Pro subscribers > Briefcase Base — 5% conversion — doubled Crustdata | B12: ='Model inputs'!Z32*'Model inputs'!Z44 -> 60
A13: Pro subscribers > Briefcase Growth | B13: ='Model inputs'!Z24*'Model inputs'!Z36 -> 400
A14: Pro subscribers > Briefcase Growth — doubled Crustdata | B14: ='Model inputs'!Z28*'Model inputs'!Z40 -> 400
A15: Pro subscribers > Briefcase Growth — 5% conversion | B15: ='Model inputs'!Z26*'Model inputs'!Z38 -> 200
A16: Pro subscribers > Briefcase Growth — 5% conversion — doubled Crustdata | B16: ='Model inputs'!Z27*'Model inputs'!Z39 -> 200
A17: MRR | B17: ='Model inputs'!C108+'Model inputs'!C6 -> 3080
A18: MRR > Briefcase Conservative | B18: ='Model inputs'!C116+'Model inputs'!C14 -> 760
A19: MRR > Briefcase Conservative — doubled Crustdata | B19: ='Model inputs'!C109+'Model inputs'!C7 -> 760
A20: MRR > Briefcase Conservative — 5% conversion | B20: ='Model inputs'!C115+'Model inputs'!C13 -> 380
A21: MRR > Briefcase Conservative — 5% conversion — doubled Crustdata | B21: ='Model inputs'!C111+'Model inputs'!C9 -> 380
A22: MRR > Briefcase Base — doubled Crustdata | B22: ='Model inputs'!C119+'Model inputs'!C17 -> 3080
A23: MRR > Briefcase Base — 5% conversion | B23: ='Model inputs'!C117+'Model inputs'!C15 -> 1940
A24: MRR > Briefcase Base — 5% conversion — doubled Crustdata | B24: ='Model inputs'!C118+'Model inputs'!C16 -> 1940
A25: MRR > Briefcase Growth | B25: ='Model inputs'!C110+'Model inputs'!C8 -> 10800
A26: MRR > Briefcase Growth — doubled Crustdata | B26: ='Model inputs'!C114+'Model inputs'!C12 -> 10800
A27: MRR > Briefcase Growth — 5% conversion | B27: ='Model inputs'!C112+'Model inputs'!C10 -> 7000
A28: MRR > Briefcase Growth — 5% conversion — doubled Crustdata | B28: ='Model inputs'!C113+'Model inputs'!C11 -> 7000
A29: Monthly COGS | B29: ='Model inputs'!C71*'Model inputs'!Z59 -> 1100
A30: Monthly COGS > Briefcase Conservative | B30: ='Model inputs'!C79*'Model inputs'!Z67 -> 264
A31: Monthly COGS > Briefcase Conservative — doubled Crustdata | B31: ='Model inputs'!C72*'Model inputs'!Z60 -> 360
A32: Monthly COGS > Briefcase Conservative — 5% conversion | B32: ='Model inputs'!C78*'Model inputs'!Z66 -> 264
A33: Monthly COGS > Briefcase Conservative — 5% conversion — doubled Crustdata | B33: ='Model inputs'!C74*'Model inputs'!Z62 -> 360
A34: Monthly COGS > Briefcase Base — doubled Crustdata | B34: ='Model inputs'!C82*'Model inputs'!Z70 -> 1500
A35: Monthly COGS > Briefcase Base — 5% conversion | B35: ='Model inputs'!C80*'Model inputs'!Z68 -> 1100
A36: Monthly COGS > Briefcase Base — 5% conversion — doubled Crustdata | B36: ='Model inputs'!C81*'Model inputs'!Z69 -> 1500
A37: Monthly COGS > Briefcase Growth | B37: ='Model inputs'!C73*'Model inputs'!Z61 -> 3960
A38: Monthly COGS > Briefcase Growth — doubled Crustdata | B38: ='Model inputs'!C77*'Model inputs'!Z65 -> 5400
A39: Monthly COGS > Briefcase Growth — 5% conversion | B39: ='Model inputs'!C75*'Model inputs'!Z63 -> 3960
A40: Monthly COGS > Briefcase Growth — 5% conversion — doubled Crustdata | B40: ='Model inputs'!C76*'Model inputs'!Z64 -> 5400
A41: Gross profit | B41: ='Model inputs'!C96-'Briefcase conversion and cost s'!B29 -> 1980
A42: Gross profit > Briefcase Conservative | B42: ='Model inputs'!C104-'Briefcase conversion and cost s'!B30 -> 496
A43: Gross profit > Briefcase Conservative — doubled Crustdata | B43: ='Model inputs'!C97-'Briefcase conversion and cost s'!B31 -> 400
A44: Gross profit > Briefcase Conservative — 5% conversion | B44: ='Model inputs'!C103-'Briefcase conversion and cost s'!B32 -> 116
A45: Gross profit > Briefcase Conservative — 5% conversion — doubled Crustdata | B45: ='Model inputs'!C99-'Briefcase conversion and cost s'!B33 -> 20
A46: Gross profit > Briefcase Base — doubled Crustdata | B46: ='Model inputs'!C107-'Briefcase conversion and cost s'!B34 -> 1580
A47: Gross profit > Briefcase Base — 5% conversion | B47: ='Model inputs'!C105-'Briefcase conversion and cost s'!B35 -> 840
A48: Gross profit > Briefcase Base — 5% conversion — doubled Crustdata | B48: ='Model inputs'!C106-'Briefcase conversion and cost s'!B36 -> 440
A49: Gross profit > Briefcase Growth | B49: ='Model inputs'!C98-'Briefcase conversion and cost s'!B37 -> 6840
A50: Gross profit > Briefcase Growth — doubled Crustdata | B50: ='Model inputs'!C102-'Briefcase conversion and cost s'!B38 -> 5400
A51: Gross profit > Briefcase Growth — 5% conversion | B51: ='Model inputs'!C100-'Briefcase conversion and cost s'!B39 -> 3040
A52: Gross profit > Briefcase Growth — 5% conversion — doubled Crustdata | B52: ='Model inputs'!C101-'Briefcase conversion and cost s'!B40 -> 1600
A53: Gross margin | B53: =IFERROR('Briefcase conversion and cost s'!B41/'Model inputs'!C96,"") -> 0.64285714
A54: Gross margin > Briefcase Conservative | B54: =IFERROR('Briefcase conversion and cost s'!B42/'Model inputs'!C104,"") -> 0.65263158
A55: Gross margin > Briefcase Conservative — doubled Crustdata | B55: =IFERROR('Briefcase conversion and cost s'!B43/'Model inputs'!C97,"") -> 0.52631579
A56: Gross margin > Briefcase Conservative — 5% conversion | B56: =IFERROR('Briefcase conversion and cost s'!B44/'Model inputs'!C103,"") -> 0.30526316
A57: Gross margin > Briefcase Conservative — 5% conversion — doubled Crustdata | B57: =IFERROR('Briefcase conversion and cost s'!B45/'Model inputs'!C99,"") -> 0.052631579
A58: Gross margin > Briefcase Base — doubled Crustdata | B58: =IFERROR('Briefcase conversion and cost s'!B46/'Model inputs'!C107,"") -> 0.51298701
A59: Gross margin > Briefcase Base — 5% conversion | B59: =IFERROR('Briefcase conversion and cost s'!B47/'Model inputs'!C105,"") -> 0.43298969
A60: Gross margin > Briefcase Base — 5% conversion — doubled Crustdata | B60: =IFERROR('Briefcase conversion and cost s'!B48/'Model inputs'!C106,"") -> 0.22680412
A61: Gross margin > Briefcase Growth | B61: =IFERROR('Briefcase conversion and cost s'!B49/'Model inputs'!C98,"") -> 0.63333333
A62: Gross margin > Briefcase Growth — doubled Crustdata | B62: =IFERROR('Briefcase conversion and cost s'!B50/'Model inputs'!C102,"") -> 0.5
A63: Gross margin > Briefcase Growth — 5% conversion | B63: =IFERROR('Briefcase conversion and cost s'!B51/'Model inputs'!C100,"") -> 0.43428571
A64: Gross margin > Briefcase Growth — 5% conversion — doubled Crustdata | B64: =IFERROR('Briefcase conversion and cost s'!B52/'Model inputs'!C101,"") -> 0.22857143
A65: Monthly cash flow | B65: ='Briefcase conversion and cost s'!B41-'Model inputs'!C84 -> 1810
A66: Monthly cash flow > Briefcase Conservative | B66: ='Briefcase conversion and cost s'!B42-'Model inputs'!C92 -> 326
A67: Monthly cash flow > Briefcase Conservative — doubled Crustdata | B67: ='Briefcase conversion and cost s'!B43-'Model inputs'!C85 -> 230
A68: Monthly cash flow > Briefcase Conservative — 5% conversion | B68: ='Briefcase conversion and cost s'!B44-'Model inputs'!C91 -> -54
A69: Monthly cash flow > Briefcase Conservative — 5% conversion — doubled Crustdata | B69: ='Briefcase conversion and cost s'!B45-'Model inputs'!C87 -> -150
A70: Monthly cash flow > Briefcase Base — doubled Crustdata | B70: ='Briefcase conversion and cost s'!B46-'Model inputs'!C95 -> 1410
A71: Monthly cash flow > Briefcase Base — 5% conversion | B71: ='Briefcase conversion and cost s'!B47-'Model inputs'!C93 -> 670
A72: Monthly cash flow > Briefcase Base — 5% conversion — doubled Crustdata | B72: ='Briefcase conversion and cost s'!B48-'Model inputs'!C94 -> 270
A73: Monthly cash flow > Briefcase Growth | B73: ='Briefcase conversion and cost s'!B49-'Model inputs'!C86 -> 6670
A74: Monthly cash flow > Briefcase Growth — doubled Crustdata | B74: ='Briefcase conversion and cost s'!B50-'Model inputs'!C90 -> 5230
A75: Monthly cash flow > Briefcase Growth — 5% conversion | B75: ='Briefcase conversion and cost s'!B51-'Model inputs'!C88 -> 2870
A76: Monthly cash flow > Briefcase Growth — 5% conversion — doubled Crustdata | B76: ='Briefcase conversion and cost s'!B52-'Model inputs'!C89 -> 1430
A77: Full-allowance cash flow | B77: ='Model inputs'!C96-'Model inputs'!C47-'Model inputs'!C84 -> -2018
A78: Full-allowance cash flow > Briefcase Conservative | B78: ='Model inputs'!C104-'Model inputs'!C55-'Model inputs'!C92 -> -906
A79: Full-allowance cash flow > Briefcase Conservative — doubled Crustdata | B79: ='Model inputs'!C97-'Model inputs'!C48-'Model inputs'!C85 -> -1450
A80: Full-allowance cash flow > Briefcase Conservative — 5% conversion | B80: ='Model inputs'!C103-'Model inputs'!C54-'Model inputs'!C91 -> -1110
A81: Full-allowance cash flow > Briefcase Conservative — 5% conversion — doubled Crustdata | B81: ='Model inputs'!C99-'Model inputs'!C50-'Model inputs'!C87 -> -1590
A82: Full-allowance cash flow > Briefcase Base — doubled Crustdata | B82: ='Model inputs'!C107-'Model inputs'!C58-'Model inputs'!C95 -> -3810
A83: Full-allowance cash flow > Briefcase Base — 5% conversion | B83: ='Model inputs'!C105-'Model inputs'!C56-'Model inputs'!C93 -> -2630
A84: Full-allowance cash flow > Briefcase Base — 5% conversion — doubled Crustdata | B84: ='Model inputs'!C106-'Model inputs'!C57-'Model inputs'!C94 -> -4230
A85: Full-allowance cash flow > Briefcase Growth | B85: ='Model inputs'!C98-'Model inputs'!C49-'Model inputs'!C86 -> -6090
A86: Full-allowance cash flow > Briefcase Growth — doubled Crustdata | B86: ='Model inputs'!C102-'Model inputs'!C53-'Model inputs'!C90 -> -12170
A87: Full-allowance cash flow > Briefcase Growth — 5% conversion | B87: ='Model inputs'!C100-'Model inputs'!C51-'Model inputs'!C88 -> -8130
A88: Full-allowance cash flow > Briefcase Growth — 5% conversion — doubled Crustdata | B88: ='Model inputs'!C101-'Model inputs'!C52-'Model inputs'!C89 -> -13570

Sheet Briefcase cash chart series
A1: Briefcase cash chart series
A2: Briefcase — Runway & decisions · Briefcase Base
A4: Variable / dimension | B4: 2026-09 | C4: 2026-10 | D4: 2026-11 | E4: 2026-12 | F4: 2027-01 | G4: 2027-02 | H4: 2027-03 | I4: 2027-04 | J4: 2027-05 | K4: 2027-06 | L4: 2027-07 | M4: 2027-08 | N4: 2027-09 | O4: 2027-10 | P4: 2027-11 | Q4: 2027-12
A5: Cash — bootstrapped | B5: =IF('Briefcase cash and runway'!B6="","",'Briefcase cash and runway'!B6) -> 0 | C5: =IF('Briefcase cash and runway'!C6="","",'Briefcase cash and runway'!C6) -> 1810 | D5: =IF('Briefcase cash and runway'!D6="","",'Briefcase cash and runway'!D6) -> 3620 | E5: =IF('Briefcase cash and runway'!E6="","",'Briefcase cash and runway'!E6) -> 5430 | F5: =IF('Briefcase cash and runway'!F6="","",'Briefcase cash and runway'!F6) -> 7240 | G5: =IF('Briefcase cash and runway'!G6="","",'Briefcase cash and runway'!G6) -> 9050 | H5: =IF('Briefcase cash and runway'!H6="","",'Briefcase cash and runway'!H6) -> 10860 | I5: =IF('Briefcase cash and runway'!I6="","",'Briefcase cash and runway'!I6) -> 12670 | ... Q5: =IF('Briefcase cash and runway'!Q6="","",'Briefcase cash and runway'!Q6) -> 27150
A6: Cash — lean launch | B6: =IF('Briefcase cash and runway'!B8="","",'Briefcase cash and runway'!B8) -> 5000 | C6: =IF('Briefcase cash and runway'!C8="","",'Briefcase cash and runway'!C8) -> 6810 | D6: =IF('Briefcase cash and runway'!D8="","",'Briefcase cash and runway'!D8) -> 8620 | E6: =IF('Briefcase cash and runway'!E8="","",'Briefcase cash and runway'!E8) -> 10430 | F6: =IF('Briefcase cash and runway'!F8="","",'Briefcase cash and runway'!F8) -> 12240 | G6: =IF('Briefcase cash and runway'!G8="","",'Briefcase cash and runway'!G8) -> 14050 | H6: =IF('Briefcase cash and runway'!H8="","",'Briefcase cash and runway'!H8) -> 15860 | I6: =IF('Briefcase cash and runway'!I8="","",'Briefcase cash and runway'!I8) -> 17670 | ... Q6: =IF('Briefcase cash and runway'!Q8="","",'Briefcase cash and runway'!Q8) -> 32150
A7: Cash — pre-seed illustration | B7: =IF('Briefcase cash and runway'!B7="","",'Briefcase cash and runway'!B7) -> 25000 | C7: =IF('Briefcase cash and runway'!C7="","",'Briefcase cash and runway'!C7) -> 26810 | D7: =IF('Briefcase cash and runway'!D7="","",'Briefcase cash and runway'!D7) -> 28620 | E7: =IF('Briefcase cash and runway'!E7="","",'Briefcase cash and runway'!E7) -> 30430 | F7: =IF('Briefcase cash and runway'!F7="","",'Briefcase cash and runway'!F7) -> 32240 | G7: =IF('Briefcase cash and runway'!G7="","",'Briefcase cash and runway'!G7) -> 34050 | H7: =IF('Briefcase cash and runway'!H7="","",'Briefcase cash and runway'!H7) -> 35860 | I7: =IF('Briefcase cash and runway'!I7="","",'Briefcase cash and runway'!I7) -> 37670 | ... Q7: =IF('Briefcase cash and runway'!Q7="","",'Briefcase cash and runway'!Q7) -> 52150

Sheet Model inputs
A1: Model inputs
A2: Integration values are aggregated snapshots; raw source records are not included.
A4: Variables
A5: Variable / segment | B5: 2026-09 | C5: 2026-10 | D5: 2026-01 | E5: 2026-02 | F5: 2026-03 | G5: 2026-04 | H5: 2026-05 | I5: 2026-06 | J5: 2026-07 | K5: 2026-08 | L5: 2026-11 | M5: 2026-12 | N5: 2027-01 | O5: 2027-02 | P5: 2027-03 | Q5: 2027-04 | R5: 2027-05 | S5: 2027-06 | T5: 2027-07 | U5: 2027-08 | V5: 2027-09 | W5: 2027-10 | X5: 2027-11 | Y5: 2027-12 | Z5: Value
A6: Career-center MRR · Briefcase Base | B6: 0 | C6: ='Model inputs'!C208*'Model inputs'!Z158 -> 800
A7: Career-center MRR · Briefcase Conservative — doubled Crustdata | C7: ='Model inputs'!C209*'Model inputs'!Z159 -> 0
A8: Career-center MRR · Briefcase Growth | C8: ='Model inputs'!C210*'Model inputs'!Z160 -> 3200
A9: Career-center MRR · Briefcase Conservative — 5% conversion — doubled Crustdata | C9: ='Model inputs'!C211*'Model inputs'!Z161 -> 0
A10: Career-center MRR · Briefcase Growth — 5% conversion | C10: ='Model inputs'!C212*'Model inputs'!Z162 -> 3200
A11: Career-center MRR · Briefcase Growth — 5% conversion — doubled Crustdata | C11: ='Model inputs'!C213*'Model inputs'!Z163 -> 3200
A12: Career-center MRR · Briefcase Growth — doubled Crustdata | C12: ='Model inputs'!C214*'Model inputs'!Z164 -> 3200
A13: Career-center MRR · Briefcase Conservative — 5% conversion | C13: ='Model inputs'!C215*'Model inputs'!Z165 -> 0
A14: Career-center MRR · Briefcase Conservative | C14: ='Model inputs'!C216*'Model inputs'!Z166 -> 0
A15: Career-center MRR · Briefcase Base — 5% conversion | C15: ='Model inputs'!C217*'Model inputs'!Z167 -> 800
A16: Career-center MRR · Briefcase Base — 5% conversion — doubled Crustdata | C16: ='Model inputs'!C218*'Model inputs'!Z168 -> 800
A17: Career-center MRR · Briefcase Base — doubled Crustdata | C17: ='Model inputs'!C219*'Model inputs'!Z169 -> 800
A18: Cash balance | B18: ="" | C18: ="" | D18: ="" | E18: ="" | F18: ="" | G18: ="" | H18: ="" | I18: ="" | ... Y18: =""
A19: Cash balance > Bootstrapped — $0 | B19: =IF('Model inputs'!Z121="","",'Model inputs'!Z121) -> 0 | C19: ='Model inputs'!B19+'Model inputs'!C83 -> 1810 | D19: =IF('Model inputs'!Z121="","",'Model inputs'!Z121) -> 0 | E19: =IF('Model inputs'!Z121="","",'Model inputs'!Z121) -> 0 | F19: =IF('Model inputs'!Z121="","",'Model inputs'!Z121) -> 0 | G19: =IF('Model inputs'!Z121="","",'Model inputs'!Z121) -> 0 | H19: =IF('Model inputs'!Z121="","",'Model inputs'!Z121) -> 0 | I19: =IF('Model inputs'!Z121="","",'Model inputs'!Z121) -> 0 | J19: =IF('Model inputs'!Z121="","",'Model inputs'!Z121) -> 0 | K19: =IF('Model inputs'!Z121="","",'Model inputs'!Z121) -> 0 | L19: ='Model inputs'!C19+'Model inputs'!L83 -> 3620 | M19: ='Model inputs'!L19+'Model inputs'!M83 -> 5430 | N19: ='Model inputs'!M19+'Model inputs'!N83 -> 7240 | O19: ='Model inputs'!N19+'Model inputs'!O83 -> 9050 | P19: ='Model inputs'!O19+'Model inputs'!P83 -> 10860 | Q19: ='Model inputs'!P19+'Model inputs'!Q83 -> 12670 | R19: ='Model inputs'!Q19+'Model inputs'!R83 -> 14480 | S19: ='Model inputs'!R19+'Model inputs'!S83 -> 16290 | T19: ='Model inputs'!S19+'Model inputs'!T83 -> 18100 | ... Y19: ='Model inputs'!X19+'Model inputs'!Y83 -> 27150
A20: Cash balance > Illustrative pre-seed — $25,000 | B20: =IF('Model inputs'!Z122="","",'Model inputs'!Z122) -> 25000 | C20: ='Model inputs'!B20+'Model inputs'!C83 -> 26810 | D20: =IF('Model inputs'!Z122="","",'Model inputs'!Z122) -> 25000 | E20: =IF('Model inputs'!Z122="","",'Model inputs'!Z122) -> 25000 | F20: =IF('Model inputs'!Z122="","",'Model inputs'!Z122) -> 25000 | G20: =IF('Model inputs'!Z122="","",'Model inputs'!Z122) -> 25000 | H20: =IF('Model inputs'!Z122="","",'Model inputs'!Z122) -> 25000 | I20: =IF('Model inputs'!Z122="","",'Model inputs'!Z122) -> 25000 | J20: =IF('Model inputs'!Z122="","",'Model inputs'!Z122) -> 25000 | K20: =IF('Model inputs'!Z122="","",'Model inputs'!Z122) -> 25000 | L20: ='Model inputs'!C20+'Model inputs'!L83 -> 28620 | M20: ='Model inputs'!L20+'Model inputs'!M83 -> 30430 | N20: ='Model inputs'!M20+'Model inputs'!N83 -> 32240 | O20: ='Model inputs'!N20+'Model inputs'!O83 -> 34050 | P20: ='Model inputs'!O20+'Model inputs'!P83 -> 35860 | Q20: ='Model inputs'!P20+'Model inputs'!Q83 -> 37670 | R20: ='Model inputs'!Q20+'Model inputs'!R83 -> 39480 | S20: ='Model inputs'!R20+'Model inputs'!S83 -> 41290 | T20: ='Model inputs'!S20+'Model inputs'!T83 -> 43100 | ... Y20: ='Model inputs'!X20+'Model inputs'!Y83 -> 52150
A21: Cash balance > Lean launch — $5,000 | B21: =IF('Model inputs'!Z123="","",'Model inputs'!Z123) -> 5000 | C21: ='Model inputs'!B21+'Model inputs'!C83 -> 6810 | D21: =IF('Model inputs'!Z123="","",'Model inputs'!Z123) -> 5000 | E21: =IF('Model inputs'!Z123="","",'Model inputs'!Z123) -> 5000 | F21: =IF('Model inputs'!Z123="","",'Model inputs'!Z123) -> 5000 | G21: =IF('Model inputs'!Z123="","",'Model inputs'!Z123) -> 5000 | H21: =IF('Model inputs'!Z123="","",'Model inputs'!Z123) -> 5000 | I21: =IF('Model inputs'!Z123="","",'Model inputs'!Z123) -> 5000 | J21: =IF('Model inputs'!Z123="","",'Model inputs'!Z123) -> 5000 | K21: =IF('Model inputs'!Z123="","",'Model inputs'!Z123) -> 5000 | L21: ='Model inputs'!C21+'Model inputs'!L83 -> 8620 | M21: ='Model inputs'!L21+'Model inputs'!M83 -> 10430 | N21: ='Model inputs'!M21+'Model inputs'!N83 -> 12240 | O21: ='Model inputs'!N21+'Model inputs'!O83 -> 14050 | P21: ='Model inputs'!O21+'Model inputs'!P83 -> 15860 | Q21: ='Model inputs'!P21+'Model inputs'!Q83 -> 17670 | R21: ='Model inputs'!Q21+'Model inputs'!R83 -> 19480 | S21: ='Model inputs'!R21+'Model inputs'!S83 -> 21290 | T21: ='Model inputs'!S21+'Model inputs'!T83 -> 23100 | ... Y21: ='Model inputs'!X21+'Model inputs'!Y83 -> 32150
A22: Free users · Briefcase Base | Z22: =1200 -> 1200
A23: Free users · Briefcase Conservative — doubled Crustdata | Z23: =400 -> 400
A24: Free users · Briefcase Growth | Z24: =4000 -> 4000
A25: Free users · Briefcase Conservative — 5% conversion — doubled Crustdata | Z25: =400 -> 400
A26: Free users · Briefcase Growth — 5% conversion | Z26: =4000 -> 4000
A27: Free users · Briefcase Growth — 5% conversion — doubled Crustdata | Z27: =4000 -> 4000
A28: Free users · Briefcase Growth — doubled Crustdata | Z28: =4000 -> 4000
A29: Free users · Briefcase Conservative — 5% conversion | Z29: =400 -> 400
A30: Free users · Briefcase Conservative | Z30: =400 -> 400
A31: Free users · Briefcase Base — 5% conversion | Z31: ='Model inputs'!Z22 -> 1200
A32: Free users · Briefcase Base — 5% conversion — doubled Crustdata | Z32: ='Model inputs'!Z22 -> 1200
A33: Free users · Briefcase Base — doubled Crustdata | Z33: ='Model inputs'!Z22 -> 1200
A34: Free-to-Pro conversion · Briefcase Base | Z34: =0.1 -> 0.1
A35: Free-to-Pro conversion · Briefcase Conservative — doubled Crustdata | Z35: ='Model inputs'!Z34 -> 0.1
A36: Free-to-Pro conversion · Briefcase Growth | Z36: ='Model inputs'!Z34 -> 0.1
A37: Free-to-Pro conversion · Briefcase Conservative — 5% conversion — doubled Crustdata | Z37: =0.05 -> 0.05
A38: Free-to-Pro conversion · Briefcase Growth — 5% conversion | Z38: =0.05 -> 0.05
A39: Free-to-Pro conversion · Briefcase Growth — 5% conversion — doubled Crustdata | Z39: =0.05 -> 0.05
A40: Free-to-Pro conversion · Briefcase Growth — doubled Crustdata | Z40: ='Model inputs'!Z34 -> 0.1
A41: Free-to-Pro conversion · Briefcase Conservative — 5% conversion | Z41: =0.05 -> 0.05
A42: Free-to-Pro conversion · Briefcase Conservative | Z42: ='Model inputs'!Z34 -> 0.1
A43: Free-to-Pro conversion · Briefcase Base — 5% conversion | Z43: =0.05 -> 0.05
A44: Free-to-Pro conversion · Briefcase Base — 5% conversion — doubled Crustdata | Z44: =0.05 -> 0.05
A45: Free-to-Pro conversion · Briefcase Base — doubled Crustdata | Z45: ='Model inputs'!Z34 -> 0.1
A46: Full-allowance cash flow | B46: 0 | C46: ='Model inputs'!C96-'Model inputs'!C47-'Model inputs'!C84 -> -2018 | L46: ='Model inputs'!L221-'Model inputs'!L206-'Model inputs'!L220 -> -2018 | M46: ='Model inputs'!M221-'Model inputs'!M206-'Model inputs'!M220 -> -2018 | N46: ='Model inputs'!N221-'Model inputs'!N206-'Model inputs'!N220 -> -2018 | O46: ='Model inputs'!O221-'Model inputs'!O206-'Model inputs'!O220 -> -2018 | P46: ='Model inputs'!P221-'Model inputs'!P206-'Model inputs'!P220 -> -2018 | Q46: ='Model inputs'!Q221-'Model inputs'!Q206-'Model inputs'!Q220 -> -2018 | R46: ='Model inputs'!R221-'Model inputs'!R206-'Model inputs'!R220 -> -2018 | S46: ='Model inputs'!S221-'Model inputs'!S206-'Model inputs'!S220 -> -2018 | ... Y46: ='Model inputs'!Y221-'Model inputs'!Y206-'Model inputs'!Y220 -> -2018
A47: Full-allowance COGS · Briefcase conversion and cost sensitivities · Briefcase Base | B47: 0 | C47: ='Model inputs'!C194*'Model inputs'!Z59 -> 4928
A48: Full-allowance COGS · Briefcase Conservative — doubled Crustdata | C48: ='Model inputs'!C195*'Model inputs'!Z60 -> 2040
A49: Full-allowance COGS · Briefcase Growth | C49: ='Model inputs'!C196*'Model inputs'!Z61 -> 16720
A50: Full-allowance COGS · Briefcase Conservative — 5% conversion — doubled Crustdata | C50: ='Model inputs'!C197*'Model inputs'!Z62 -> 1800
A51: Full-allowance COGS · Briefcase Growth — 5% conversion | C51: ='Model inputs'!C198*'Model inputs'!Z63 -> 14960
A52: Full-allowance COGS · Briefcase Growth — 5% conversion — doubled Crustdata | C52: ='Model inputs'!C199*'Model inputs'!Z64 -> 20400
A53: Full-allowance COGS · Briefcase Growth — doubled Crustdata | C53: ='Model inputs'!C200*'Model inputs'!Z65 -> 22800
A54: Full-allowance COGS · Briefcase Conservative — 5% conversion | C54: ='Model inputs'!C201*'Model inputs'!Z66 -> 1320
A55: Full-allowance COGS · Briefcase Conservative | C55: ='Model inputs'!C202*'Model inputs'!Z67 -> 1496
A56: Full-allowance COGS · Briefcase Base — 5% conversion | C56: ='Model inputs'!C203*'Model inputs'!Z68 -> 4400
A57: Full-allowance COGS · Briefcase Base — 5% conversion — doubled Crustdata | C57: ='Model inputs'!C204*'Model inputs'!Z69 -> 6000
A58: Full-allowance COGS · Briefcase Base — doubled Crustdata | C58: ='Model inputs'!C205*'Model inputs'!Z70 -> 6720
A59: Modeled cost per brief · Briefcase conversion and cost sensitivities · Briefcase Base | Z59: ='Model inputs'!Z134+'Model inputs'!Z170-'Model inputs'!Z146 -> 0.22
A60: Modeled cost per brief · Briefcase Conservative — doubled Crustdata | Z60: ='Model inputs'!Z135+'Model inputs'!Z171-'Model inputs'!Z147 -> 0.3
A61: Modeled cost per brief · Briefcase Growth | Z61: ='Model inputs'!Z136+'Model inputs'!Z172-'Model inputs'!Z148 -> 0.22
A62: Modeled cost per brief · Briefcase Conservative — 5% conversion — doubled Crustdata | Z62: ='Model inputs'!Z137+'Model inputs'!Z173-'Model inputs'!Z149 -> 0.3
A63: Modeled cost per brief · Briefcase Growth — 5% conversion | Z63: ='Model inputs'!Z138+'Model inputs'!Z174-'Model inputs'!Z150 -> 0.22
A64: Modeled cost per brief · Briefcase Growth — 5% conversion — doubled Crustdata | Z64: ='Model inputs'!Z139+'Model inputs'!Z175-'Model inputs'!Z151 -> 0.3
A65: Modeled cost per brief · Briefcase Growth — doubled Crustdata | Z65: ='Model inputs'!Z140+'Model inputs'!Z176-'Model inputs'!Z152 -> 0.3
A66: Modeled cost per brief · Briefcase Conservative — 5% conversion | Z66: ='Model inputs'!Z141+'Model inputs'!Z177-'Model inputs'!Z153 -> 0.22
A67: Modeled cost per brief · Briefcase Conservative | Z67: ='Model inputs'!Z142+'Model inputs'!Z178-'Model inputs'!Z154 -> 0.22
A68: Modeled cost per brief · Briefcase Base — 5% conversion | Z68: ='Model inputs'!Z143+'Model inputs'!Z179-'Model inputs'!Z155 -> 0.22
A69: Modeled cost per brief · Briefcase Base — 5% conversion — doubled Crustdata | Z69: ='Model inputs'!Z144+'Model inputs'!Z180-'Model inputs'!Z156 -> 0.3
A70: Modeled cost per brief · Briefcase Base — doubled Crustdata | Z70: ='Model inputs'!Z145+'Model inputs'!Z181-'Model inputs'!Z157 -> 0.3
A71: Monthly briefs · Briefcase conversion and cost sensitivities · Briefcase Base | B71: 0 | C71: =IF('Model inputs'!Z246="","",'Model inputs'!Z246) -> 5000
A72: Monthly briefs · Briefcase Conservative — doubled Crustdata | C72: =IF('Model inputs'!Z247="","",'Model inputs'!Z247) -> 1200
A73: Monthly briefs · Briefcase Growth | C73: =IF('Model inputs'!Z248="","",'Model inputs'!Z248) -> 18000
A74: Monthly briefs · Briefcase Conservative — 5% conversion — doubled Crustdata | C74: =IF('Model inputs'!Z249="","",'Model inputs'!Z249) -> 1200
A75: Monthly briefs · Briefcase Growth — 5% conversion | C75: =IF('Model inputs'!Z250="","",'Model inputs'!Z250) -> 18000
A76: Monthly briefs · Briefcase Growth — 5% conversion — doubled Crustdata | C76: =IF('Model inputs'!Z251="","",'Model inputs'!Z251) -> 18000
A77: Monthly briefs · Briefcase Growth — doubled Crustdata | C77: =IF('Model inputs'!Z252="","",'Model inputs'!Z252) -> 18000
A78: Monthly briefs · Briefcase Conservative — 5% conversion | C78: =IF('Model inputs'!Z253="","",'Model inputs'!Z253) -> 1200
A79: Monthly briefs · Briefcase Conservative | C79: =IF('Model inputs'!Z254="","",'Model inputs'!Z254) -> 1200
A80: Monthly briefs · Briefcase Base — 5% conversion | C80: =IF('Model inputs'!Z255="","",'Model inputs'!Z255) -> 5000
A81: Monthly briefs · Briefcase Base — 5% conversion — doubled Crustdata | C81: =IF('Model inputs'!Z256="","",'Model inputs'!Z256) -> 5000
A82: Monthly briefs · Briefcase Base — doubled Crustdata | C82: =IF('Model inputs'!Z257="","",'Model inputs'!Z257) -> 5000
A83: Monthly cash flow · Briefcase cash and runway | B83: 0 | C83: ='Model inputs'!C124-'Model inputs'!C84 -> 1810 | L83: ='Model inputs'!L207-'Model inputs'!L220 -> 1810 | M83: ='Model inputs'!M207-'Model inputs'!M220 -> 1810 | N83: ='Model inputs'!N207-'Model inputs'!N220 -> 1810 | O83: ='Model inputs'!O207-'Model inputs'!O220 -> 1810 | P83: ='Model inputs'!P207-'Model inputs'!P220 -> 1810 | Q83: ='Model inputs'!Q207-'Model inputs'!Q220 -> 1810 | R83: ='Model inputs'!R207-'Model inputs'!R220 -> 1810 | S83: ='Model inputs'!S207-'Model inputs'!S220 -> 1810 | ... Y83: ='Model inputs'!Y207-'Model inputs'!Y220 -> 1810
A84: Monthly fixed Opex · Briefcase conversion and cost sensitivities · Briefcase Base | B84: 0 | C84: =IF('Model inputs'!Z182="","",'Model inputs'!Z182) -> 170
A85: Monthly fixed Opex · Briefcase Conservative — doubled Crustdata | C85: =IF('Model inputs'!Z183="","",'Model inputs'!Z183) -> 170
A86: Monthly fixed Opex · Briefcase Growth | C86: =IF('Model inputs'!Z184="","",'Model inputs'!Z184) -> 170
A87: Monthly fixed Opex · Briefcase Conservative — 5% conversion — doubled Crustdata | C87: =IF('Model inputs'!Z185="","",'Model inputs'!Z185) -> 170
A88: Monthly fixed Opex · Briefcase Growth — 5% conversion | C88: =IF('Model inputs'!Z186="","",'Model inputs'!Z186) -> 170
A89: Monthly fixed Opex · Briefcase Growth — 5% conversion — doubled Crustdata | C89: =IF('Model inputs'!Z187="","",'Model inputs'!Z187) -> 170
A90: Monthly fixed Opex · Briefcase Growth — doubled Crustdata | C90: =IF('Model inputs'!Z188="","",'Model inputs'!Z188) -> 170
A91: Monthly fixed Opex · Briefcase Conservative — 5% conversion | C91: =IF('Model inputs'!Z189="","",'Model inputs'!Z189) -> 170
A92: Monthly fixed Opex · Briefcase Conservative | C92: =IF('Model inputs'!Z190="","",'Model inputs'!Z190) -> 170
A93: Monthly fixed Opex · Briefcase Base — 5% conversion | C93: =IF('Model inputs'!Z191="","",'Model inputs'!Z191) -> 170
A94: Monthly fixed Opex · Briefcase Base — 5% conversion — doubled Crustdata | C94: =IF('Model inputs'!Z192="","",'Model inputs'!Z192) -> 170
A95: Monthly fixed Opex · Briefcase Base — doubled Crustdata | C95: =IF('Model inputs'!Z193="","",'Model inputs'!Z193) -> 170
A96: Monthly revenue · Briefcase conversion and cost sensitivities · Briefcase Base | B96: 0 | C96: ='Model inputs'!C259+'Model inputs'!C222 -> 3080
A97: Monthly revenue · Briefcase Conservative — doubled Crustdata | C97: ='Briefcase conversion and cost s'!B19+'Model inputs'!C223 -> 760
A98: Monthly revenue · Briefcase Growth | C98: ='Briefcase conversion and cost s'!B25+'Model inputs'!C224 -> 10800
A99: Monthly revenue · Briefcase Conservative — 5% conversion — doubled Crustdata | C99: ='Briefcase conversion and cost s'!B21+'Model inputs'!C225 -> 380
A100: Monthly revenue · Briefcase Growth — 5% conversion | C100: ='Briefcase conversion and cost s'!B27+'Model inputs'!C226 -> 7000
A101: Monthly revenue · Briefcase Growth — 5% conversion — doubled Crustdata | C101: ='Briefcase conversion and cost s'!B28+'Model inputs'!C227 -> 7000
...
